{"stats":{"originHTML":"\n\t<h2 class=\"pi-item pi-header pi-secondary-font pi-item-spacing pi-secondary-background\">Stats</h2>\n\n<div class=\"pi-item pi-data pi-item-spacing pi-border-color\" data-source=\"ad\">\n\t\n\t<div class=\"pi-data-value pi-font\">+25 <a href=\"/wiki/Attack_damage\" title=\"Attack damage\">attack damage</a></div>\n</div>\n\n<div class=\"pi-item pi-data pi-item-spacing pi-border-color\" data-source=\"hp\">\n\t\n\t<div class=\"pi-data-value pi-font\">+150 <a href=\"/wiki/Health\" title=\"Health\">health</a></div>\n</div>\n\n<div class=\"pi-item pi-data pi-item-spacing pi-border-color\" data-source=\"lifesteal\">\n\t\n\t<div class=\"pi-data-value pi-font\">+7% <a href=\"/wiki/Life_steal\" title=\"Life steal\">life steal</a></div>\n</div>\n\n","values":["+25 attack damage","+150 health","+7% life steal"]},"active":{},"passive":{"originHTML":"\n\t<h2 class=\"pi-item pi-header pi-secondary-font pi-item-spacing pi-secondary-background\">Passive</h2>\n\n<div class=\"pi-item pi-data pi-item-spacing pi-border-color\" data-source=\"pass\">\n\t\n\t<div class=\"pi-data-value pi-font\"><span class=\"template_sbc\"><b>Unique – <a href=\"/wiki/Named_item_effect#Legendary\" title=\"Named item effect\">Legendary</a>:</b></span> This item counts as a Legendary item.</div>\n</div>\n\n","originText":"UNIQUE – LEGENDARY: This item counts as a Legendary item."},"consume":{},"recipe":{"1":[["Cost"," 950"],["Sell"," 665"],["ID","3184"]]},"availability":{},"tags":{},"name":"Guardian's Hammer","link":"https://leagueoflegends.fandom.com/wiki/Guardian%27s_Hammer"}