{"Aatrox":{"hp":650,"hp_plus":114,"hp5":3,"hp5_plus":1,"mp":0,"mp_plus":0,"mp5":0,"mp5_plus":0,"ad":60,"ad_plus":5,"as":0.651,"as_plus":0.025,"ar":38,"ar_plus":4.45,"mr":32,"mr_plus":2.05,"ms":345,"range":175},"Ahri":{"hp":570,"hp_plus":96,"hp5":2.5,"hp5_plus":0.6,"mp":418,"mp_plus":25,"mp5":8,"mp5_plus":0.8,"ad":53,"ad_plus":3,"as":0.668,"as_plus":0.02,"ar":18,"ar_plus":4.7,"mr":30,"mr_plus":1.3,"ms":330,"range":550},"Akali":{"hp":570,"hp_plus":119,"hp5":9,"hp5_plus":0.9,"mp":200,"mp_plus":0,"mp5":50,"mp5_plus":0,"ad":62,"ad_plus":3.3,"as":0.625,"as_plus":0.032,"ar":23,"ar_plus":4.7,"mr":37,"mr_plus":2.05,"ms":345,"range":125},"Akshan":{"hp":630,"hp_plus":104,"hp5":3.75,"hp5_plus":0.65,"mp":350,"mp_plus":40,"mp5":8.175,"mp5_plus":0.7,"ad":52,"ad_plus":3.5,"as":0.638,"as_plus":0.04,"ar":26,"ar_plus":4.2,"mr":30,"mr_plus":1.3,"ms":330,"range":500},"Alistar":{"hp":670,"hp_plus":120,"hp5":8.5,"hp5_plus":0.85,"mp":350,"mp_plus":40,"mp5":8.5,"mp5_plus":0.8,"ad":62,"ad_plus":3.75,"as":0.625,"as_plus":0.02125,"ar":44,"ar_plus":4.7,"mr":32,"mr_plus":2.05,"ms":330,"range":125},"Amumu":{"hp":685,"hp_plus":89,"hp5":9,"hp5_plus":0.85,"mp":285,"mp_plus":40,"mp5":7.38,"mp5_plus":0.53,"ad":53,"ad_plus":3.8,"as":0.736,"as_plus":0.0218,"ar":30,"ar_plus":4.2,"mr":32,"mr_plus":2.05,"ms":335,"range":125},"Anivia":{"hp":550,"hp_plus":96,"hp5":5.5,"hp5_plus":0.55,"mp":495,"mp_plus":45,"mp5":8,"mp5_plus":0.8,"ad":51,"ad_plus":3.2,"as":0.625,"as_plus":0.0168,"ar":21,"ar_plus":5.2,"mr":30,"mr_plus":1.3,"ms":325,"range":600},"Annie":{"hp":594,"hp_plus":102,"hp5":5.5,"hp5_plus":0.55,"mp":418,"mp_plus":25,"mp5":8,"mp5_plus":0.8,"ad":50,"ad_plus":2.63,"as":0.579,"as_plus":0.013600000000000001,"ar":19,"ar_plus":5.2,"mr":30,"mr_plus":1.3,"ms":335,"range":625},"Aphelios":{"hp":580,"hp_plus":102,"hp5":3.25,"hp5_plus":0.55,"mp":348,"mp_plus":42,"mp5":6.5,"mp5_plus":0.4,"ad":55,"ad_plus":3,"as":0.64,"as_plus":0.021,"ar":26,"ar_plus":4.2,"mr":30,"mr_plus":1.3,"ms":325,"range":550},"Ashe":{"hp":640,"hp_plus":101,"hp5":3.5,"hp5_plus":0.55,"mp":280,"mp_plus":32,"mp5":6.97,"mp5_plus":0.4,"ad":59,"ad_plus":2.96,"as":0.658,"as_plus":0.0333,"ar":26,"ar_plus":4.6,"mr":30,"mr_plus":1.3,"ms":325,"range":600},"AurelionSol":{"hp":645,"hp_plus":106,"hp5":7,"hp5_plus":0.6,"mp":350,"mp_plus":50,"mp5":6,"mp5_plus":0.8,"ad":57,"ad_plus":3.2,"as":0.625,"as_plus":0.013600000000000001,"ar":19,"ar_plus":4.8,"mr":30,"mr_plus":1.3,"ms":325,"range":550},"Azir":{"hp":622,"hp_plus":119,"hp5":7,"hp5_plus":0.75,"mp":480,"mp_plus":21,"mp5":8,"mp5_plus":0.8,"ad":52,"ad_plus":2.8,"as":0.625,"as_plus":0.03,"ar":19,"ar_plus":4.2,"mr":30,"mr_plus":1.3,"ms":335,"range":525},"Bard":{"hp":630,"hp_plus":103,"hp5":5.5,"hp5_plus":0.55,"mp":350,"mp_plus":50,"mp5":6,"mp5_plus":0.45,"ad":52,"ad_plus":3,"as":0.625,"as_plus":0.02,"ar":34,"ar_plus":5.2,"mr":30,"mr_plus":1.3,"ms":330,"range":500},"Bel'Veth":{"hp":610,"hp_plus":99,"hp5":6,"hp5_plus":0.6,"mp":0,"mp_plus":0,"mp5":0,"mp5_plus":0,"ad":60,"ad_plus":1.7,"as":0.85,"as_plus":0,"ar":32,"ar_plus":4.7,"mr":32,"mr_plus":2.05,"ms":340,"range":175},"Blitzcrank":{"hp":653,"hp_plus":109,"hp5":7.5,"hp5_plus":0.75,"mp":267,"mp_plus":40,"mp5":8.5,"mp5_plus":0.8,"ad":62,"ad_plus":3.5,"as":0.625,"as_plus":0.0113,"ar":40,"ar_plus":4.7,"mr":32,"mr_plus":2.05,"ms":325,"range":125},"Brand":{"hp":590,"hp_plus":102,"hp5":5.5,"hp5_plus":0.55,"mp":469,"mp_plus":21,"mp5":10.67,"mp5_plus":0.6,"ad":57,"ad_plus":3,"as":0.625,"as_plus":0.013600000000000001,"ar":22,"ar_plus":4.7,"mr":30,"mr_plus":1.3,"ms":340,"range":550},"Braum":{"hp":610,"hp_plus":112,"hp5":8.5,"hp5_plus":1,"mp":311,"mp_plus":45,"mp5":6,"mp5_plus":0.8,"ad":55,"ad_plus":3.2,"as":0.644,"as_plus":0.035,"ar":47,"ar_plus":5.2,"mr":32,"mr_plus":2.05,"ms":335,"range":125},"Caitlyn":{"hp":580,"hp_plus":107,"hp5":3.5,"hp5_plus":0.55,"mp":315,"mp_plus":35,"mp5":7.4,"mp5_plus":0.55,"ad":62,"ad_plus":3.8,"as":0.681,"as_plus":0.04,"ar":28,"ar_plus":4.7,"mr":30,"mr_plus":1.3,"ms":325,"range":650},"Camille":{"hp":646,"hp_plus":99,"hp5":8.5,"hp5_plus":0.8,"mp":339,"mp_plus":52,"mp5":8.15,"mp5_plus":0.75,"ad":68,"ad_plus":3.5,"as":0.644,"as_plus":0.025,"ar":35,"ar_plus":5,"mr":32.1,"mr_plus":2.05,"ms":340,"range":125},"Cassiopeia":{"hp":630,"hp_plus":104,"hp5":5.5,"hp5_plus":0.5,"mp":350,"mp_plus":60,"mp5":8,"mp5_plus":0.8,"ad":53,"ad_plus":3,"as":0.647,"as_plus":0.015,"ar":18,"ar_plus":4.7,"mr":32,"mr_plus":1.3,"ms":328,"range":550},"Cho'Gath":{"hp":644,"hp_plus":94,"hp5":9,"hp5_plus":0.85,"mp":270,"mp_plus":60,"mp5":7.2,"mp5_plus":0.45,"ad":69,"ad_plus":4.2,"as":0.625,"as_plus":0.0144,"ar":38,"ar_plus":4.7,"mr":32,"mr_plus":2.05,"ms":345,"range":125},"Corki":{"hp":588,"hp_plus":101,"hp5":5.5,"hp5_plus":0.55,"mp":350,"mp_plus":54,"mp5":7.42,"mp5_plus":0.55,"ad":55,"ad_plus":2.5,"as":0.638,"as_plus":0.023,"ar":28,"ar_plus":4.7,"mr":30,"mr_plus":1.3,"ms":325,"range":550},"Darius":{"hp":652,"hp_plus":114,"hp5":10,"hp5_plus":0.95,"mp":263,"mp_plus":57.5,"mp5":6.6,"mp5_plus":0.35,"ad":64,"ad_plus":5,"as":0.625,"as_plus":0.01,"ar":39,"ar_plus":5.2,"mr":32,"mr_plus":2.05,"ms":340,"range":175},"Diana":{"hp":640,"hp_plus":109,"hp5":6.5,"hp5_plus":0.85,"mp":375,"mp_plus":25,"mp5":8,"mp5_plus":0.8,"ad":57,"ad_plus":3,"as":0.625,"as_plus":0.0225,"ar":31,"ar_plus":4.3,"mr":32,"mr_plus":2.05,"ms":345,"range":150},"Dr.Mundo":{"hp":653,"hp_plus":103,"hp5":6.5,"hp5_plus":0.75,"mp":0,"mp_plus":0,"mp5":0,"mp5_plus":0,"ad":61,"ad_plus":3.5,"as":0.72,"as_plus":0.033,"ar":32,"ar_plus":4.2,"mr":32,"mr_plus":2.05,"ms":345,"range":125},"Draven":{"hp":675,"hp_plus":104,"hp5":3.75,"hp5_plus":0.7,"mp":360.56,"mp_plus":39,"mp5":8.04,"mp5_plus":0.65,"ad":62,"ad_plus":3.61,"as":0.679,"as_plus":0.027000000000000003,"ar":29,"ar_plus":4.5,"mr":30,"mr_plus":1.3,"ms":330,"range":550},"Ekko":{"hp":655,"hp_plus":99,"hp5":9,"hp5_plus":0.9,"mp":280,"mp_plus":70,"mp5":7,"mp5_plus":0.8,"ad":58,"ad_plus":3,"as":0.688,"as_plus":0.033,"ar":32,"ar_plus":4.2,"mr":32,"mr_plus":2.05,"ms":340,"range":125},"Elise":{"hp":650,"hp_plus":109,"hp5":5.5,"hp5_plus":0.6,"mp":324,"mp_plus":50,"mp5":6,"mp5_plus":0.8,"ad":55,"ad_plus":3,"as":0.625,"as_plus":0.0175,"ar":30,"ar_plus":5.2,"mr":30,"mr_plus":1.3,"ms":330,"range":550},"Evelynn":{"hp":642,"hp_plus":98,"hp5":8.5,"hp5_plus":0.75,"mp":315,"mp_plus":42,"mp5":8.11,"mp5_plus":0.6,"ad":61,"ad_plus":3,"as":0.667,"as_plus":0.021,"ar":37,"ar_plus":4.7,"mr":32.1,"mr_plus":2.05,"ms":335,"range":125},"Ezreal":{"hp":600,"hp_plus":102,"hp5":4,"hp5_plus":0.65,"mp":375,"mp_plus":70,"mp5":8.5,"mp5_plus":0.65,"ad":60,"ad_plus":2.5,"as":0.625,"as_plus":0.025,"ar":24,"ar_plus":4.7,"mr":30,"mr_plus":1.3,"ms":325,"range":550},"Fiddlesticks":{"hp":650.4,"hp_plus":106,"hp5":5.5,"hp5_plus":0.6,"mp":500,"mp_plus":28,"mp5":8,"mp5_plus":0.8,"ad":55.36,"ad_plus":2.63,"as":0.625,"as_plus":0.021099999999999997,"ar":34,"ar_plus":4.7,"mr":30,"mr_plus":1.3,"ms":335,"range":480},"Fiora":{"hp":620,"hp_plus":99,"hp5":8.5,"hp5_plus":0.55,"mp":300,"mp_plus":60,"mp5":8,"mp5_plus":0.7,"ad":68,"ad_plus":3.3,"as":0.69,"as_plus":0.032,"ar":33,"ar_plus":4.7,"mr":32,"mr_plus":2.05,"ms":345,"range":150},"Fizz":{"hp":640,"hp_plus":106,"hp5":8,"hp5_plus":0.7,"mp":317,"mp_plus":52,"mp5":6,"mp5_plus":0.8,"ad":58,"ad_plus":3,"as":0.658,"as_plus":0.031,"ar":22,"ar_plus":4.6,"mr":32,"mr_plus":2.05,"ms":335,"range":175},"Galio":{"hp":632,"hp_plus":126,"hp5":8,"hp5_plus":0.8,"mp":500,"mp_plus":40,"mp5":9.5,"mp5_plus":0.7,"ad":59,"ad_plus":3.5,"as":0.625,"as_plus":0.015,"ar":24,"ar_plus":4.7,"mr":32,"mr_plus":2.05,"ms":335,"range":150},"Gangplank":{"hp":600,"hp_plus":114,"hp5":6,"hp5_plus":0.6,"mp":280,"mp_plus":60,"mp5":7.5,"mp5_plus":0.7,"ad":64,"ad_plus":4,"as":0.658,"as_plus":0.032,"ar":31,"ar_plus":4.2,"mr":32,"mr_plus":2.05,"ms":345,"range":125},"Garen":{"hp":690,"hp_plus":98,"hp5":8,"hp5_plus":0.5,"mp":0,"mp_plus":0,"mp5":0,"mp5_plus":0,"ad":66,"ad_plus":4.5,"as":0.625,"as_plus":0.0365,"ar":36,"ar_plus":4.2,"mr":32,"mr_plus":1.55,"ms":340,"range":175},"Gnar":{"hp":540,"hp_plus":79,"hp5":4.5,"hp5_plus":1.25,"mp":100,"mp_plus":0,"mp5":0,"mp5_plus":0,"ad":57,"ad_plus":3,"as":0.625,"as_plus":0.06,"ar":32,"ar_plus":3.7,"mr":30,"mr_plus":1.3,"ms":335,"range":400},"Gragas":{"hp":670,"hp_plus":109,"hp5":5.5,"hp5_plus":0.5,"mp":400,"mp_plus":47,"mp5":6,"mp5_plus":0.8,"ad":64,"ad_plus":3.5,"as":0.675,"as_plus":0.020499999999999997,"ar":38,"ar_plus":4.8,"mr":32,"mr_plus":2.05,"ms":330,"range":125},"Graves":{"hp":625,"hp_plus":106,"hp5":8,"hp5_plus":0.7,"mp":325,"mp_plus":40,"mp5":8,"mp5_plus":0.7,"ad":68,"ad_plus":4,"as":0.475,"as_plus":0.026000000000000002,"ar":33,"ar_plus":4.6,"mr":32,"mr_plus":2.05,"ms":340,"range":425},"Gwen":{"hp":620,"hp_plus":109,"hp5":8.5,"hp5_plus":0.9,"mp":330,"mp_plus":40,"mp5":7.5,"mp5_plus":0.7,"ad":63,"ad_plus":3,"as":0.69,"as_plus":0.0225,"ar":39,"ar_plus":5.2,"mr":32,"mr_plus":2.05,"ms":340,"range":150},"Hecarim":{"hp":650,"hp_plus":104,"hp5":7,"hp5_plus":0.75,"mp":277,"mp_plus":60,"mp5":6.5,"mp5_plus":0.6,"ad":66,"ad_plus":3.2,"as":0.67,"as_plus":0.025,"ar":35,"ar_plus":5.45,"mr":32,"mr_plus":2.05,"ms":345,"range":175},"Heimerdinger":{"hp":558,"hp_plus":101,"hp5":7,"hp5_plus":0.55,"mp":385,"mp_plus":20,"mp5":8,"mp5_plus":0.8,"ad":56,"ad_plus":2.7,"as":0.625,"as_plus":0.013600000000000001,"ar":19,"ar_plus":4.2,"mr":30,"mr_plus":1.3,"ms":340,"range":550},"Illaoi":{"hp":656,"hp_plus":109,"hp5":9.5,"hp5_plus":0.8,"mp":300,"mp_plus":50,"mp5":7.5,"mp5_plus":0.75,"ad":68,"ad_plus":5,"as":0.625,"as_plus":0.025,"ar":35,"ar_plus":5,"mr":32,"mr_plus":2.05,"ms":350,"range":125},"Irelia":{"hp":590,"hp_plus":124,"hp5":8.5,"hp5_plus":0.85,"mp":350,"mp_plus":50,"mp5":8,"mp5_plus":0.8,"ad":65,"ad_plus":4,"as":0.656,"as_plus":0.025,"ar":36,"ar_plus":4.2,"mr":28,"mr_plus":2.05,"ms":335,"range":200},"Ivern":{"hp":655,"hp_plus":99,"hp5":7,"hp5_plus":0.85,"mp":450,"mp_plus":60,"mp5":6,"mp5_plus":0.75,"ad":50,"ad_plus":3,"as":0.644,"as_plus":0.034,"ar":27,"ar_plus":4.7,"mr":32,"mr_plus":2.05,"ms":330,"range":475},"Janna":{"hp":570,"hp_plus":84,"hp5":5.5,"hp5_plus":0.55,"mp":350,"mp_plus":64,"mp5":11.5,"mp5_plus":0.4,"ad":52,"ad_plus":3,"as":0.625,"as_plus":0.03,"ar":28,"ar_plus":5,"mr":30,"mr_plus":1.3,"ms":325,"range":500},"JarvanIV":{"hp":640,"hp_plus":104,"hp5":8,"hp5_plus":0.7,"mp":300,"mp_plus":55,"mp5":6.5,"mp5_plus":0.45,"ad":64,"ad_plus":3.4,"as":0.658,"as_plus":0.025,"ar":34,"ar_plus":4.8,"mr":32,"mr_plus":2.05,"ms":340,"range":175},"Jax":{"hp":685,"hp_plus":99,"hp5":8.5,"hp5_plus":0.55,"mp":339,"mp_plus":52,"mp5":7.58,"mp5_plus":0.7,"ad":68,"ad_plus":4.25,"as":0.638,"as_plus":0.034,"ar":36,"ar_plus":4.2,"mr":32,"mr_plus":2.05,"ms":350,"range":125},"Jayce":{"hp":590,"hp_plus":109,"hp5":6,"hp5_plus":0.6,"mp":375,"mp_plus":45,"mp5":6,"mp5_plus":0.8,"ad":54,"ad_plus":4.25,"as":0.658,"as_plus":0.03,"ar":22,"ar_plus":5,"mr":30,"mr_plus":1.3,"ms":335,"range":125},"Jhin":{"hp":655,"hp_plus":107,"hp5":3.75,"hp5_plus":0.55,"mp":300,"mp_plus":50,"mp5":6,"mp5_plus":0.8,"ad":59,"ad_plus":4.7,"as":0.625,"as_plus":0.03,"ar":24,"ar_plus":4.7,"mr":30,"mr_plus":1.3,"ms":330,"range":550},"Jinx":{"hp":630,"hp_plus":100,"hp5":3.75,"hp5_plus":0.5,"mp":245,"mp_plus":45,"mp5":6.7,"mp5_plus":1,"ad":57,"ad_plus":3.4,"as":0.625,"as_plus":0.01,"ar":26,"ar_plus":4.7,"mr":30,"mr_plus":1.3,"ms":325,"range":525},"Kai'Sa":{"hp":670,"hp_plus":102,"hp5":3.5,"hp5_plus":0.55,"mp":344.88,"mp_plus":38,"mp5":8.2,"mp5_plus":0.45,"ad":59,"ad_plus":2,"as":0.644,"as_plus":0.018000000000000002,"ar":28,"ar_plus":4.2,"mr":30,"mr_plus":1.3,"ms":335,"range":525},"Kalista":{"hp":604,"hp_plus":114,"hp5":3.75,"hp5_plus":0.55,"mp":300,"mp_plus":45,"mp5":6.3,"mp5_plus":0.4,"ad":66,"ad_plus":3.5,"as":0.694,"as_plus":0.045,"ar":24,"ar_plus":5.2,"mr":30,"mr_plus":1.3,"ms":330,"range":525},"Karma":{"hp":604,"hp_plus":109,"hp5":5.5,"hp5_plus":0.55,"mp":374,"mp_plus":50,"mp5":13,"mp5_plus":0.5,"ad":51,"ad_plus":3.3,"as":0.625,"as_plus":0.023,"ar":28,"ar_plus":5,"mr":30,"mr_plus":1.3,"ms":335,"range":525},"Karthus":{"hp":620,"hp_plus":110,"hp5":6.5,"hp5_plus":0.55,"mp":467,"mp_plus":30.5,"mp5":8,"mp5_plus":0.8,"ad":46,"ad_plus":3.25,"as":0.625,"as_plus":0.021099999999999997,"ar":21,"ar_plus":4.7,"mr":30,"mr_plus":1.3,"ms":335,"range":450},"Kassadin":{"hp":646,"hp_plus":119,"hp5":6,"hp5_plus":0.5,"mp":400,"mp_plus":87,"mp5":6,"mp5_plus":0.8,"ad":59,"ad_plus":3.9,"as":0.64,"as_plus":0.037000000000000005,"ar":19,"ar_plus":4,"mr":30,"mr_plus":1.3,"ms":335,"range":150},"Katarina":{"hp":672,"hp_plus":108,"hp5":7.5,"hp5_plus":0.7,"mp":0,"mp_plus":0,"mp5":0,"mp5_plus":0,"ad":58,"ad_plus":3.2,"as":0.658,"as_plus":0.0274,"ar":28,"ar_plus":4.7,"mr":32,"mr_plus":2.05,"ms":335,"range":125},"Kayle":{"hp":670,"hp_plus":92,"hp5":5,"hp5_plus":0.5,"mp":330,"mp_plus":50,"mp5":8,"mp5_plus":0.8,"ad":50,"ad_plus":2.5,"as":0.625,"as_plus":0.015,"ar":26,"ar_plus":4.2,"mr":22,"mr_plus":1.3,"ms":335,"range":175},"Kayn":{"hp":655,"hp_plus":109,"hp5":8,"hp5_plus":0.75,"mp":410,"mp_plus":50,"mp5":11.5,"mp5_plus":0.95,"ad":68,"ad_plus":3.3,"as":0.669,"as_plus":0.027000000000000003,"ar":38,"ar_plus":4.5,"mr":32,"mr_plus":2.05,"ms":340,"range":175},"Kennen":{"hp":611,"hp_plus":98,"hp5":5.5,"hp5_plus":0.65,"mp":200,"mp_plus":0,"mp5":50,"mp5_plus":0,"ad":48,"ad_plus":3.75,"as":0.625,"as_plus":0.034,"ar":29,"ar_plus":4.95,"mr":30,"mr_plus":1.3,"ms":335,"range":550},"Kha'Zix":{"hp":643,"hp_plus":99,"hp5":7.5,"hp5_plus":0.75,"mp":327,"mp_plus":40,"mp5":7.59,"mp5_plus":0.5,"ad":63,"ad_plus":3.1,"as":0.668,"as_plus":0.027000000000000003,"ar":36,"ar_plus":4.2,"mr":32,"mr_plus":2.05,"ms":350,"range":125},"Kindred":{"hp":610,"hp_plus":99,"hp5":7,"hp5_plus":0.55,"mp":300,"mp_plus":35,"mp5":7,"mp5_plus":0.4,"ad":65,"ad_plus":2.5,"as":0.625,"as_plus":0.035,"ar":29,"ar_plus":4.7,"mr":30,"mr_plus":1.3,"ms":325,"range":500},"Kled":{"hp":410,"hp_plus":84,"hp5":6,"hp5_plus":0.75,"mp":100,"mp_plus":0,"mp5":0,"mp5_plus":0,"ad":65,"ad_plus":3.5,"as":0.625,"as_plus":0.035,"ar":35,"ar_plus":5.2,"mr":28,"mr_plus":2.05,"ms":285,"range":250},"Kled&Skaarl":{"hp":810,"hp_plus":144,"hp5":6,"hp5_plus":0.75,"mp":100,"mp_plus":0,"mp5":0,"mp5_plus":0,"ad":65,"ad_plus":3.5,"as":0.625,"as_plus":0.035,"ar":35,"ar_plus":5.2,"mr":28,"mr_plus":2.05,"ms":345,"range":125},"Kog'Maw":{"hp":635,"hp_plus":99,"hp5":3.75,"hp5_plus":0.55,"mp":325,"mp_plus":40,"mp5":8.75,"mp5_plus":0.7,"ad":61,"ad_plus":3.11,"as":0.665,"as_plus":0.0265,"ar":24,"ar_plus":4.45,"mr":30,"mr_plus":1.3,"ms":330,"range":500},"LeBlanc":{"hp":598,"hp_plus":111,"hp5":7.5,"hp5_plus":0.55,"mp":400,"mp_plus":55,"mp5":6,"mp5_plus":0.8,"ad":55,"ad_plus":3.5,"as":0.625,"as_plus":0.013999999999999999,"ar":22,"ar_plus":4.7,"mr":30,"mr_plus":1.3,"ms":340,"range":525},"LeeSin":{"hp":645,"hp_plus":99,"hp5":7.5,"hp5_plus":0.7,"mp":200,"mp_plus":0,"mp5":50,"mp5_plus":0,"ad":68,"ad_plus":3.7,"as":0.651,"as_plus":0.03,"ar":36,"ar_plus":4.9,"mr":32,"mr_plus":2.05,"ms":345,"range":125},"Leona":{"hp":646,"hp_plus":101,"hp5":8.5,"hp5_plus":0.85,"mp":302,"mp_plus":40,"mp5":6,"mp5_plus":0.8,"ad":60,"ad_plus":3,"as":0.625,"as_plus":0.028999999999999998,"ar":47,"ar_plus":4.8,"mr":32,"mr_plus":2.05,"ms":335,"range":125},"Lillia":{"hp":625,"hp_plus":104,"hp5":2.5,"hp5_plus":0.55,"mp":410,"mp_plus":50,"mp5":11.5,"mp5_plus":0.95,"ad":61,"ad_plus":3.1,"as":0.625,"as_plus":0.027000000000000003,"ar":22,"ar_plus":5.2,"mr":32,"mr_plus":1.55,"ms":330,"range":325},"Lissandra":{"hp":620,"hp_plus":104,"hp5":7,"hp5_plus":0.55,"mp":475,"mp_plus":30,"mp5":8,"mp5_plus":0.4,"ad":55,"ad_plus":2.7,"as":0.656,"as_plus":0.013600000000000001,"ar":22,"ar_plus":4.9,"mr":30,"mr_plus":1.3,"ms":325,"range":550},"Lucian":{"hp":641,"hp_plus":100,"hp5":3.75,"hp5_plus":0.65,"mp":348.88,"mp_plus":38,"mp5":8.18,"mp5_plus":0.7,"ad":60,"ad_plus":2.9,"as":0.638,"as_plus":0.033,"ar":28,"ar_plus":4.2,"mr":30,"mr_plus":1.3,"ms":335,"range":500},"Lulu":{"hp":595,"hp_plus":88,"hp5":6,"hp5_plus":0.6,"mp":350,"mp_plus":55,"mp5":11,"mp5_plus":0.6,"ad":47,"ad_plus":2.6,"as":0.625,"as_plus":0.0225,"ar":29,"ar_plus":4.9,"mr":30,"mr_plus":1.3,"ms":330,"range":550},"Lux":{"hp":560,"hp_plus":99,"hp5":5.5,"hp5_plus":0.55,"mp":480,"mp_plus":23.5,"mp5":8,"mp5_plus":0.8,"ad":54,"ad_plus":3.3,"as":0.669,"as_plus":0.02,"ar":19,"ar_plus":5.2,"mr":30,"mr_plus":1.3,"ms":330,"range":550},"Malphite":{"hp":644,"hp_plus":104,"hp5":7,"hp5_plus":0.55,"mp":280,"mp_plus":60,"mp5":7.32,"mp5_plus":0.55,"ad":62,"ad_plus":4,"as":0.736,"as_plus":0.034,"ar":37,"ar_plus":4.95,"mr":28,"mr_plus":2.05,"ms":335,"range":125},"Malzahar":{"hp":580,"hp_plus":101,"hp5":6,"hp5_plus":0.6,"mp":375,"mp_plus":27.5,"mp5":8,"mp5_plus":0.8,"ad":55,"ad_plus":3,"as":0.625,"as_plus":0.015,"ar":18,"ar_plus":4.7,"mr":30,"mr_plus":1.3,"ms":335,"range":500},"Maokai":{"hp":635,"hp_plus":109,"hp5":5,"hp5_plus":0.75,"mp":375,"mp_plus":43,"mp5":7.2,"mp5_plus":0.6,"ad":64,"ad_plus":3.3,"as":0.8,"as_plus":0.02125,"ar":39,"ar_plus":5.2,"mr":32,"mr_plus":2.05,"ms":335,"range":125},"MasterYi":{"hp":669,"hp_plus":100,"hp5":7.5,"hp5_plus":0.65,"mp":251,"mp_plus":42,"mp5":7.26,"mp5_plus":0.45,"ad":65,"ad_plus":2.5,"as":0.679,"as_plus":0.02,"ar":33,"ar_plus":4.2,"mr":32,"mr_plus":2.05,"ms":355,"range":175},"MegaGnar":{"hp":640,"hp_plus":122,"hp5":4.5,"hp5_plus":1.25,"mp":100,"mp_plus":0,"mp5":0,"mp5_plus":0,"ad":65,"ad_plus":5.5,"as":0.625,"as_plus":0.005,"ar":35.5,"ar_plus":6.7,"mr":33.5,"mr_plus":4.8,"ms":335,"range":175},"MissFortune":{"hp":640,"hp_plus":107,"hp5":3.75,"hp5_plus":0.65,"mp":300,"mp_plus":35,"mp5":8.04,"mp5_plus":0.65,"ad":52,"ad_plus":2.7,"as":0.656,"as_plus":0.03,"ar":28,"ar_plus":4.2,"mr":30,"mr_plus":1.3,"ms":325,"range":550},"Mordekaiser":{"hp":645,"hp_plus":104,"hp5":5,"hp5_plus":0.75,"mp":0,"mp_plus":0,"mp5":0,"mp5_plus":0,"ad":61,"ad_plus":4,"as":0.625,"as_plus":0.01,"ar":37,"ar_plus":4.2,"mr":32,"mr_plus":2.05,"ms":335,"range":175},"Morgana":{"hp":630,"hp_plus":104,"hp5":5.5,"hp5_plus":0.4,"mp":340,"mp_plus":60,"mp5":11,"mp5_plus":0.4,"ad":56,"ad_plus":3.5,"as":0.625,"as_plus":0.015300000000000001,"ar":25,"ar_plus":5,"mr":30,"mr_plus":1.3,"ms":335,"range":450},"Nami":{"hp":560,"hp_plus":88,"hp5":5.5,"hp5_plus":0.55,"mp":365,"mp_plus":43,"mp5":11.5,"mp5_plus":0.4,"ad":51,"ad_plus":3.1,"as":0.644,"as_plus":0.026099999999999998,"ar":29,"ar_plus":5.2,"mr":30,"mr_plus":1.3,"ms":335,"range":550},"Nasus":{"hp":631,"hp_plus":104,"hp5":9,"hp5_plus":0.9,"mp":326,"mp_plus":62,"mp5":7.44,"mp5_plus":0.5,"ad":67,"ad_plus":3.5,"as":0.638,"as_plus":0.0348,"ar":34,"ar_plus":4.7,"mr":32,"mr_plus":2.05,"ms":350,"range":125},"Nautilus":{"hp":646,"hp_plus":100,"hp5":8.5,"hp5_plus":0.55,"mp":400,"mp_plus":47,"mp5":8.63,"mp5_plus":0.5,"ad":61,"ad_plus":3.3,"as":0.706,"as_plus":0.01,"ar":39,"ar_plus":4.95,"mr":32,"mr_plus":2.05,"ms":325,"range":175},"Neeko":{"hp":610,"hp_plus":104,"hp5":7.5,"hp5_plus":0.75,"mp":450,"mp_plus":30,"mp5":7,"mp5_plus":0.7,"ad":48,"ad_plus":2.5,"as":0.625,"as_plus":0.035,"ar":21,"ar_plus":5.2,"mr":30,"mr_plus":1.3,"ms":340,"range":550},"Nidalee":{"hp":610,"hp_plus":109,"hp5":6,"hp5_plus":0.6,"mp":295,"mp_plus":45,"mp5":6,"mp5_plus":0.8,"ad":58,"ad_plus":3.5,"as":0.638,"as_plus":0.0322,"ar":28,"ar_plus":4.7,"mr":30,"mr_plus":1.3,"ms":335,"range":525},"Nilah":{"hp":570,"hp_plus":101,"hp5":4,"hp5_plus":0.18,"mp":350,"mp_plus":35,"mp5":8.18,"mp5_plus":0.7,"ad":58,"ad_plus":2,"as":0.697,"as_plus":0.03,"ar":27,"ar_plus":4.2,"mr":32,"mr_plus":2.05,"ms":340,"range":225},"Nocturne":{"hp":655,"hp_plus":109,"hp5":7,"hp5_plus":0.75,"mp":275,"mp_plus":35,"mp5":7,"mp5_plus":0.45,"ad":62,"ad_plus":3.1,"as":0.721,"as_plus":0.027000000000000003,"ar":38,"ar_plus":4.7,"mr":32,"mr_plus":1.55,"ms":345,"range":125},"Nunu&Willump":{"hp":610,"hp_plus":90,"hp5":5,"hp5_plus":0.8,"mp":280,"mp_plus":42,"mp5":7,"mp5_plus":0.5,"ad":61,"ad_plus":3,"as":0.625,"as_plus":0.0225,"ar":29,"ar_plus":4.2,"mr":32,"mr_plus":2.05,"ms":345,"range":125},"Olaf":{"hp":645,"hp_plus":119,"hp5":6.5,"hp5_plus":0.6,"mp":316,"mp_plus":50,"mp5":7.5,"mp5_plus":0.6,"ad":68,"ad_plus":4.7,"as":0.694,"as_plus":0.027000000000000003,"ar":35,"ar_plus":4.2,"mr":32,"mr_plus":2.05,"ms":350,"range":125},"Orianna":{"hp":600,"hp_plus":105,"hp5":7,"hp5_plus":0.55,"mp":418,"mp_plus":25,"mp5":8,"mp5_plus":0.8,"ad":40,"ad_plus":2.6,"as":0.658,"as_plus":0.035,"ar":17,"ar_plus":4.2,"mr":26,"mr_plus":1.3,"ms":325,"range":525},"Ornn":{"hp":660,"hp_plus":109,"hp5":9,"hp5_plus":0.9,"mp":340.6,"mp_plus":65,"mp5":8.01,"mp5_plus":0.6,"ad":69,"ad_plus":3.5,"as":0.625,"as_plus":0.02,"ar":33,"ar_plus":5.2,"mr":32,"mr_plus":2.05,"ms":335,"range":175},"Pantheon":{"hp":650,"hp_plus":109,"hp5":7.5,"hp5_plus":0.65,"mp":317.12,"mp_plus":31,"mp5":7.36,"mp5_plus":0.45,"ad":64,"ad_plus":3.3,"as":0.644,"as_plus":0.029500000000000002,"ar":40,"ar_plus":4.95,"mr":28,"mr_plus":2.05,"ms":345,"range":175},"Poppy":{"hp":610,"hp_plus":104,"hp5":8,"hp5_plus":0.8,"mp":280,"mp_plus":40,"mp5":7,"mp5_plus":0.7,"ad":64,"ad_plus":4,"as":0.625,"as_plus":0.025,"ar":38,"ar_plus":4.7,"mr":32,"mr_plus":2.05,"ms":345,"range":125},"Pyke":{"hp":670,"hp_plus":104,"hp5":7,"hp5_plus":0.5,"mp":415,"mp_plus":50,"mp5":8,"mp5_plus":1,"ad":62,"ad_plus":2,"as":0.667,"as_plus":0.025,"ar":45,"ar_plus":4.7,"mr":32,"mr_plus":2.05,"ms":330,"range":150},"Qiyana":{"hp":590,"hp_plus":124,"hp5":6,"hp5_plus":0.9,"mp":320,"mp_plus":50,"mp5":8,"mp5_plus":0.7,"ad":66,"ad_plus":3.1,"as":0.688,"as_plus":0.021,"ar":28,"ar_plus":4.7,"mr":32,"mr_plus":2.05,"ms":335,"range":150},"Quinn":{"hp":603,"hp_plus":99,"hp5":5.5,"hp5_plus":0.55,"mp":269,"mp_plus":35,"mp5":6.97,"mp5_plus":0.4,"ad":59,"ad_plus":2.4,"as":0.668,"as_plus":0.031,"ar":28,"ar_plus":4.7,"mr":30,"mr_plus":1.3,"ms":335,"range":525},"Rakan":{"hp":610,"hp_plus":99,"hp5":5,"hp5_plus":0.5,"mp":315,"mp_plus":50,"mp5":8.75,"mp5_plus":0.5,"ad":62,"ad_plus":3.5,"as":0.635,"as_plus":0.03,"ar":32,"ar_plus":5.1,"mr":32,"mr_plus":2.05,"ms":335,"range":300},"Rammus":{"hp":634,"hp_plus":94,"hp5":8,"hp5_plus":0.55,"mp":310,"mp_plus":33,"mp5":7.84,"mp5_plus":0.5,"ad":56,"ad_plus":3.5,"as":0.656,"as_plus":0.02215,"ar":36,"ar_plus":5.5,"mr":32,"mr_plus":2.05,"ms":335,"range":125},"Rek'Sai":{"hp":640,"hp_plus":99,"hp5":7.5,"hp5_plus":0.65,"mp":100,"mp_plus":0,"mp5":0,"mp5_plus":0,"ad":64,"ad_plus":3,"as":0.667,"as_plus":0.02,"ar":36,"ar_plus":4.95,"mr":32,"mr_plus":2.05,"ms":335,"range":175},"Rell":{"hp":610,"hp_plus":104,"hp5":7,"hp5_plus":0.55,"mp":350,"mp_plus":45,"mp5":6,"mp5_plus":0.35,"ad":55,"ad_plus":3,"as":0.55,"as_plus":0.02,"ar":32,"ar_plus":4.2,"mr":32.1,"mr_plus":2.05,"ms":335,"range":175},"RenataGlasc":{"hp":545,"hp_plus":94,"hp5":5.5,"hp5_plus":0.55,"mp":350,"mp_plus":50,"mp5":11.5,"mp5_plus":0.5,"ad":49,"ad_plus":3,"as":0.625,"as_plus":0.021099999999999997,"ar":27,"ar_plus":4.7,"mr":30,"mr_plus":1.3,"ms":330,"range":550},"Renekton":{"hp":660,"hp_plus":111,"hp5":8,"hp5_plus":0.75,"mp":100,"mp_plus":0,"mp5":0,"mp5_plus":0,"ad":69,"ad_plus":4.15,"as":0.665,"as_plus":0.0275,"ar":35,"ar_plus":5.2,"mr":32,"mr_plus":2.05,"ms":345,"range":125},"Rengar":{"hp":620,"hp_plus":104,"hp5":7,"hp5_plus":0.5,"mp":4,"mp_plus":0,"mp5":0,"mp5_plus":0,"ad":68,"ad_plus":3,"as":0.667,"as_plus":0.03,"ar":34,"ar_plus":4.2,"mr":32,"mr_plus":2.05,"ms":345,"range":125},"Riven":{"hp":630,"hp_plus":100,"hp5":8.5,"hp5_plus":0.5,"mp":0,"mp_plus":0,"mp5":0,"mp5_plus":0,"ad":64,"ad_plus":3,"as":0.625,"as_plus":0.035,"ar":33,"ar_plus":4.4,"mr":32,"mr_plus":2.05,"ms":340,"range":125},"Rumble":{"hp":659,"hp_plus":99,"hp5":8,"hp5_plus":0.6,"mp":100,"mp_plus":0,"mp5":0,"mp5_plus":0,"ad":61,"ad_plus":3.2,"as":0.644,"as_plus":0.018500000000000003,"ar":36,"ar_plus":4.7,"mr":28,"mr_plus":1.55,"ms":345,"range":125},"Ryze":{"hp":645,"hp_plus":124,"hp5":8,"hp5_plus":0.8,"mp":300,"mp_plus":70,"mp5":8,"mp5_plus":1,"ad":58,"ad_plus":3,"as":0.625,"as_plus":0.02112,"ar":22,"ar_plus":4.2,"mr":36,"mr_plus":1.3,"ms":340,"range":550},"Samira":{"hp":600,"hp_plus":108,"hp5":3.25,"hp5_plus":0.55,"mp":348.88,"mp_plus":38,"mp5":8.18,"mp5_plus":0.7,"ad":57,"ad_plus":3.3,"as":0.658,"as_plus":0.033,"ar":26,"ar_plus":4.7,"mr":30,"mr_plus":1.3,"ms":335,"range":500},"Sejuani":{"hp":630,"hp_plus":114,"hp5":8.5,"hp5_plus":1,"mp":400,"mp_plus":40,"mp5":7,"mp5_plus":0.7,"ad":66,"ad_plus":4,"as":0.688,"as_plus":0.035,"ar":34,"ar_plus":5.45,"mr":32,"mr_plus":2.05,"ms":340,"range":150},"Senna":{"hp":530,"hp_plus":89,"hp5":3.5,"hp5_plus":0.55,"mp":350,"mp_plus":45,"mp5":11.5,"mp5_plus":0.4,"ad":50,"ad_plus":0,"as":0.625,"as_plus":0.04,"ar":28,"ar_plus":4.7,"mr":30,"mr_plus":1.3,"ms":330,"range":600},"Seraphine":{"hp":570,"hp_plus":104,"hp5":6.5,"hp5_plus":0.6,"mp":440,"mp_plus":40,"mp5":8,"mp5_plus":1,"ad":55,"ad_plus":3,"as":0.669,"as_plus":0.01,"ar":19,"ar_plus":4.2,"mr":30,"mr_plus":1.3,"ms":325,"range":525},"Sett":{"hp":670,"hp_plus":114,"hp5":7,"hp5_plus":0.5,"mp":0,"mp_plus":0,"mp5":0,"mp5_plus":0,"ad":60,"ad_plus":4,"as":0.625,"as_plus":0.0175,"ar":33,"ar_plus":5.2,"mr":32,"mr_plus":2.05,"ms":340,"range":125},"Shaco":{"hp":630,"hp_plus":99,"hp5":8.5,"hp5_plus":0.55,"mp":297,"mp_plus":40,"mp5":7.16,"mp5_plus":0.45,"ad":63,"ad_plus":3,"as":0.694,"as_plus":0.03,"ar":30,"ar_plus":4,"mr":32,"mr_plus":2.05,"ms":345,"range":125},"Shen":{"hp":610,"hp_plus":99,"hp5":8.5,"hp5_plus":0.75,"mp":400,"mp_plus":0,"mp5":50,"mp5_plus":0,"ad":60,"ad_plus":3,"as":0.751,"as_plus":0.03,"ar":34,"ar_plus":4.2,"mr":32,"mr_plus":2.05,"ms":340,"range":125},"Shyvana":{"hp":665,"hp_plus":109,"hp5":8.5,"hp5_plus":0.8,"mp":100,"mp_plus":0,"mp5":0,"mp5_plus":0,"ad":66,"ad_plus":3.4,"as":0.658,"as_plus":0.025,"ar":38,"ar_plus":4.55,"mr":32,"mr_plus":2.05,"ms":350,"range":125},"Singed":{"hp":650,"hp_plus":99,"hp5":9.5,"hp5_plus":0.55,"mp":330,"mp_plus":45,"mp5":7.5,"mp5_plus":0.55,"ad":63,"ad_plus":3.38,"as":0.613,"as_plus":0.019,"ar":34,"ar_plus":4.7,"mr":32,"mr_plus":2.05,"ms":345,"range":125},"Sion":{"hp":615,"hp_plus":87,"hp5":7.5,"hp5_plus":0.8,"mp":330,"mp_plus":42,"mp5":8,"mp5_plus":0.6,"ad":68,"ad_plus":4,"as":0.679,"as_plus":0.013000000000000001,"ar":32,"ar_plus":4.2,"mr":32,"mr_plus":2.05,"ms":345,"range":175},"Sivir":{"hp":600,"hp_plus":104,"hp5":3.25,"hp5_plus":0.55,"mp":340,"mp_plus":40,"mp5":6,"mp5_plus":0.8,"ad":58,"ad_plus":3,"as":0.625,"as_plus":0.02,"ar":26,"ar_plus":4.45,"mr":30,"mr_plus":1.3,"ms":335,"range":500},"Skarner":{"hp":650,"hp_plus":99,"hp5":9,"hp5_plus":0.85,"mp":320,"mp_plus":60,"mp5":7.2,"mp5_plus":0.45,"ad":65,"ad_plus":4.5,"as":0.625,"as_plus":0.021,"ar":38,"ar_plus":5,"mr":32,"mr_plus":2.05,"ms":335,"range":125},"Sona":{"hp":550,"hp_plus":91,"hp5":5.5,"hp5_plus":0.55,"mp":340,"mp_plus":45,"mp5":11.5,"mp5_plus":0.4,"ad":49,"ad_plus":3,"as":0.644,"as_plus":0.023,"ar":26,"ar_plus":4.2,"mr":30,"mr_plus":1.3,"ms":325,"range":550},"Soraka":{"hp":605,"hp_plus":88,"hp5":2.5,"hp5_plus":0.5,"mp":425,"mp_plus":40,"mp5":11.5,"mp5_plus":0.4,"ad":50,"ad_plus":3,"as":0.625,"as_plus":0.021400000000000002,"ar":32,"ar_plus":5,"mr":30,"mr_plus":1.3,"ms":325,"range":550},"Swain":{"hp":595,"hp_plus":99,"hp5":7,"hp5_plus":0.65,"mp":468,"mp_plus":28.5,"mp5":8,"mp5_plus":0.8,"ad":58,"ad_plus":2.7,"as":0.625,"as_plus":0.021099999999999997,"ar":26,"ar_plus":5.2,"mr":30,"mr_plus":1.3,"ms":330,"range":525},"Sylas":{"hp":595,"hp_plus":129,"hp5":9,"hp5_plus":0.9,"mp":310,"mp_plus":70,"mp5":8,"mp5_plus":0.8,"ad":61,"ad_plus":3,"as":0.645,"as_plus":0.035,"ar":27,"ar_plus":5.2,"mr":32,"mr_plus":2.55,"ms":340,"range":175},"Syndra":{"hp":593,"hp_plus":104,"hp5":6.5,"hp5_plus":0.6,"mp":480,"mp_plus":40,"mp5":8,"mp5_plus":0.8,"ad":54,"ad_plus":2.9,"as":0.625,"as_plus":0.02,"ar":25,"ar_plus":4.6,"mr":30,"mr_plus":1.3,"ms":330,"range":550},"TahmKench":{"hp":640,"hp_plus":103,"hp5":6.5,"hp5_plus":0.55,"mp":325,"mp_plus":50,"mp5":8,"mp5_plus":1,"ad":56,"ad_plus":3.2,"as":0.658,"as_plus":0.025,"ar":42,"ar_plus":4.7,"mr":32,"mr_plus":2.05,"ms":335,"range":175},"Taliyah":{"hp":550,"hp_plus":104,"hp5":6.5,"hp5_plus":0.65,"mp":470,"mp_plus":30,"mp5":8,"mp5_plus":0.8,"ad":58,"ad_plus":3.3,"as":0.625,"as_plus":0.013600000000000001,"ar":18,"ar_plus":4.7,"mr":30,"mr_plus":1.3,"ms":330,"range":525},"Talon":{"hp":658,"hp_plus":109,"hp5":8.5,"hp5_plus":0.75,"mp":377.2,"mp_plus":37,"mp5":7.6,"mp5_plus":0.8,"ad":68,"ad_plus":3.1,"as":0.625,"as_plus":0.028999999999999998,"ar":30,"ar_plus":4.7,"mr":39,"mr_plus":2.05,"ms":335,"range":125},"Taric":{"hp":645,"hp_plus":99,"hp5":6,"hp5_plus":0.5,"mp":300,"mp_plus":60,"mp5":8.5,"mp5_plus":0.8,"ad":55,"ad_plus":3.5,"as":0.625,"as_plus":0.02,"ar":40,"ar_plus":4.6,"mr":32,"mr_plus":2.05,"ms":340,"range":150},"Teemo":{"hp":598,"hp_plus":104,"hp5":5.5,"hp5_plus":0.65,"mp":334,"mp_plus":25,"mp5":9.6,"mp5_plus":0.45,"ad":54,"ad_plus":3,"as":0.69,"as_plus":0.0338,"ar":24,"ar_plus":4.95,"mr":30,"mr_plus":1.3,"ms":330,"range":500},"Thresh":{"hp":600,"hp_plus":115,"hp5":7,"hp5_plus":0.55,"mp":274,"mp_plus":44,"mp5":6,"mp5_plus":0.8,"ad":56,"ad_plus":2.2,"as":0.625,"as_plus":0.035,"ar":28,"ar_plus":0,"mr":30,"mr_plus":1.3,"ms":330,"range":450},"Tristana":{"hp":670,"hp_plus":102,"hp5":4,"hp5_plus":0.65,"mp":250,"mp_plus":32,"mp5":7.2,"mp5_plus":0.45,"ad":59,"ad_plus":3.7,"as":0.656,"as_plus":0.015,"ar":26,"ar_plus":4.2,"mr":30,"mr_plus":1.3,"ms":325,"range":525},"Trundle":{"hp":686,"hp_plus":110,"hp5":6,"hp5_plus":0.75,"mp":281,"mp_plus":45,"mp5":7.5,"mp5_plus":0.6,"ad":68,"ad_plus":3,"as":0.67,"as_plus":0.028999999999999998,"ar":37,"ar_plus":3.9,"mr":32,"mr_plus":2.05,"ms":350,"range":175},"Tryndamere":{"hp":696,"hp_plus":112,"hp5":8.5,"hp5_plus":0.9,"mp":100,"mp_plus":0,"mp5":0,"mp5_plus":0,"ad":72,"ad_plus":3.7,"as":0.67,"as_plus":0.028999999999999998,"ar":33,"ar_plus":4.3,"mr":32,"mr_plus":2.05,"ms":345,"range":125},"TwistedFate":{"hp":604,"hp_plus":108,"hp5":5.5,"hp5_plus":0.6,"mp":333,"mp_plus":39,"mp5":8,"mp5_plus":0.8,"ad":52,"ad_plus":3.3,"as":0.651,"as_plus":0.0322,"ar":21,"ar_plus":4.35,"mr":30,"mr_plus":1.3,"ms":330,"range":525},"Twitch":{"hp":682,"hp_plus":100,"hp5":3.75,"hp5_plus":0.6,"mp":287.2,"mp_plus":40,"mp5":7.26,"mp5_plus":0.45,"ad":59,"ad_plus":3.11,"as":0.679,"as_plus":0.0338,"ar":27,"ar_plus":4.2,"mr":30,"mr_plus":1.3,"ms":330,"range":550},"Udyr":{"hp":664,"hp_plus":106,"hp5":6,"hp5_plus":0.75,"mp":271,"mp_plus":50,"mp5":7.5,"mp5_plus":0.45,"ad":62,"ad_plus":4,"as":0.649,"as_plus":0.03,"ar":34,"ar_plus":5.2,"mr":32,"mr_plus":2.05,"ms":350,"range":125},"Urgot":{"hp":655,"hp_plus":102,"hp5":7.5,"hp5_plus":0.7,"mp":340,"mp_plus":45,"mp5":7.25,"mp5_plus":0.8,"ad":63,"ad_plus":4,"as":0.625,"as_plus":0.0375,"ar":36,"ar_plus":5.45,"mr":32,"mr_plus":2.05,"ms":330,"range":350},"Varus":{"hp":600,"hp_plus":105,"hp5":3.5,"hp5_plus":0.55,"mp":360,"mp_plus":40,"mp5":8,"mp5_plus":0.8,"ad":62,"ad_plus":3.4,"as":0.658,"as_plus":0.04,"ar":27,"ar_plus":4.6,"mr":30,"mr_plus":1.3,"ms":330,"range":575},"Vayne":{"hp":550,"hp_plus":103,"hp5":3.5,"hp5_plus":0.55,"mp":231.8,"mp_plus":35,"mp5":6.97,"mp5_plus":0.4,"ad":60,"ad_plus":2.36,"as":0.658,"as_plus":0.033,"ar":23,"ar_plus":4.6,"mr":30,"mr_plus":1.3,"ms":330,"range":550},"Veigar":{"hp":575,"hp_plus":108,"hp5":6.5,"hp5_plus":0.6,"mp":490,"mp_plus":26,"mp5":8,"mp5_plus":0.8,"ad":52,"ad_plus":2.7,"as":0.625,"as_plus":0.022400000000000003,"ar":21,"ar_plus":5.2,"mr":32,"mr_plus":1.3,"ms":340,"range":550},"Vel'Koz":{"hp":590,"hp_plus":102,"hp5":5.5,"hp5_plus":0.55,"mp":469,"mp_plus":21,"mp5":8,"mp5_plus":0.8,"ad":55,"ad_plus":3.1415927,"as":0.625,"as_plus":0.013600000000000001,"ar":22,"ar_plus":4.7,"mr":30,"mr_plus":1.3,"ms":340,"range":525},"Vex":{"hp":590,"hp_plus":104,"hp5":6.5,"hp5_plus":0.6,"mp":490,"mp_plus":32,"mp5":6,"mp5_plus":0.8,"ad":54,"ad_plus":2.75,"as":0.669,"as_plus":0.01,"ar":23,"ar_plus":4.45,"mr":28,"mr_plus":1.3,"ms":335,"range":550},"Vi":{"hp":655,"hp_plus":99,"hp5":10,"hp5_plus":1,"mp":295,"mp_plus":65,"mp5":8,"mp5_plus":0.65,"ad":63,"ad_plus":3,"as":0.644,"as_plus":0.02,"ar":30,"ar_plus":4.7,"mr":32,"mr_plus":2.05,"ms":340,"range":125},"Viego":{"hp":630,"hp_plus":109,"hp5":7,"hp5_plus":0.7,"mp":0,"mp_plus":0,"mp5":0,"mp5_plus":0,"ad":57,"ad_plus":3.5,"as":0.658,"as_plus":0.025,"ar":34,"ar_plus":5.2,"mr":32,"mr_plus":2.05,"ms":345,"range":200},"Viktor":{"hp":600,"hp_plus":104,"hp5":8,"hp5_plus":0.65,"mp":405,"mp_plus":45,"mp5":8,"mp5_plus":0.8,"ad":53,"ad_plus":3,"as":0.658,"as_plus":0.021099999999999997,"ar":23,"ar_plus":5.2,"mr":30,"mr_plus":1.3,"ms":335,"range":525},"Vladimir":{"hp":607,"hp_plus":110,"hp5":7,"hp5_plus":0.6,"mp":2,"mp_plus":0,"mp5":0,"mp5_plus":0,"ad":55,"ad_plus":3,"as":0.658,"as_plus":0.02,"ar":27,"ar_plus":4.5,"mr":30,"mr_plus":1.3,"ms":330,"range":450},"Volibear":{"hp":650,"hp_plus":104,"hp5":9,"hp5_plus":0.75,"mp":350,"mp_plus":70,"mp5":6.25,"mp5_plus":0.5,"ad":60,"ad_plus":3.5,"as":0.625,"as_plus":0.02,"ar":31,"ar_plus":5.2,"mr":32,"mr_plus":2.05,"ms":340,"range":150},"Warwick":{"hp":620,"hp_plus":99,"hp5":4,"hp5_plus":0.75,"mp":280,"mp_plus":35,"mp5":7.47,"mp5_plus":0.58,"ad":65,"ad_plus":3,"as":0.638,"as_plus":0.023,"ar":33,"ar_plus":4.4,"mr":32,"mr_plus":2.05,"ms":335,"range":125},"Wukong":{"hp":610,"hp_plus":99,"hp5":3.5,"hp5_plus":0.65,"mp":300,"mp_plus":65,"mp5":8,"mp5_plus":0.65,"ad":68,"ad_plus":3.5,"as":0.711,"as_plus":0.03,"ar":31,"ar_plus":4.7,"mr":28,"mr_plus":2.05,"ms":345,"range":175},"Xayah":{"hp":660,"hp_plus":102,"hp5":3.25,"hp5_plus":0.75,"mp":340,"mp_plus":40,"mp5":8.25,"mp5_plus":0.75,"ad":60,"ad_plus":3.5,"as":0.625,"as_plus":0.039,"ar":25,"ar_plus":4.2,"mr":30,"mr_plus":1.3,"ms":330,"range":525},"Xerath":{"hp":596,"hp_plus":106,"hp5":5.5,"hp5_plus":0.55,"mp":459,"mp_plus":22,"mp5":8,"mp5_plus":0.8,"ad":55,"ad_plus":3,"as":0.625,"as_plus":0.013600000000000001,"ar":22,"ar_plus":4.7,"mr":30,"mr_plus":1.3,"ms":340,"range":525},"XinZhao":{"hp":640,"hp_plus":106,"hp5":8,"hp5_plus":0.7,"mp":274,"mp_plus":55,"mp5":7.26,"mp5_plus":0.45,"ad":63,"ad_plus":3,"as":0.645,"as_plus":0.035,"ar":35,"ar_plus":4.7,"mr":32,"mr_plus":2.05,"ms":345,"range":175},"Yasuo":{"hp":590,"hp_plus":101,"hp5":6.5,"hp5_plus":0.9,"mp":100,"mp_plus":0,"mp5":0,"mp5_plus":0,"ad":60,"ad_plus":3,"as":0.697,"as_plus":0.035,"ar":30,"ar_plus":4.6,"mr":32,"mr_plus":2.05,"ms":345,"range":175},"Yone":{"hp":620,"hp_plus":99,"hp5":7.5,"hp5_plus":0.75,"mp":500,"mp_plus":0,"mp5":0,"mp5_plus":0,"ad":60,"ad_plus":2,"as":0.625,"as_plus":0.035,"ar":28,"ar_plus":4.6,"mr":32,"mr_plus":2.05,"ms":345,"range":175},"Yorick":{"hp":650,"hp_plus":114,"hp5":8,"hp5_plus":0.8,"mp":300,"mp_plus":60,"mp5":7.5,"mp5_plus":0.75,"ad":62,"ad_plus":5,"as":0.625,"as_plus":0.02,"ar":39,"ar_plus":5.2,"mr":32,"mr_plus":2.05,"ms":340,"range":175},"Yuumi":{"hp":550,"hp_plus":84,"hp5":7,"hp5_plus":0.55,"mp":400,"mp_plus":45,"mp5":10,"mp5_plus":0.4,"ad":55,"ad_plus":3.1,"as":0.625,"as_plus":0.01,"ar":25,"ar_plus":4.2,"mr":25,"mr_plus":1.1,"ms":330,"range":500},"Zac":{"hp":685,"hp_plus":109,"hp5":8,"hp5_plus":0.5,"mp":0,"mp_plus":0,"mp5":0,"mp5_plus":0,"ad":60,"ad_plus":3.4,"as":0.736,"as_plus":0.016,"ar":33,"ar_plus":4.7,"mr":32,"mr_plus":2.05,"ms":340,"range":175},"Zed":{"hp":654,"hp_plus":99,"hp5":7,"hp5_plus":0.65,"mp":200,"mp_plus":0,"mp5":50,"mp5_plus":0,"ad":63,"ad_plus":3.4,"as":0.651,"as_plus":0.033,"ar":32,"ar_plus":4.7,"mr":32,"mr_plus":2.05,"ms":345,"range":125},"Zeri":{"hp":600,"hp_plus":109,"hp5":3.25,"hp5_plus":0.7,"mp":250,"mp_plus":45,"mp5":6,"mp5_plus":0.8,"ad":50,"ad_plus":1.5,"as":0.658,"as_plus":0.02,"ar":20,"ar_plus":4.2,"mr":30,"mr_plus":1.3,"ms":325,"range":500},"Ziggs":{"hp":606,"hp_plus":106,"hp5":6.5,"hp5_plus":0.6,"mp":480,"mp_plus":23.5,"mp5":8,"mp5_plus":0.8,"ad":54,"ad_plus":3.1,"as":0.656,"as_plus":0.02,"ar":22,"ar_plus":4.5,"mr":30,"mr_plus":1.3,"ms":325,"range":550},"Zilean":{"hp":574,"hp_plus":96,"hp5":5.5,"hp5_plus":0.5,"mp":452,"mp_plus":50,"mp5":11.34,"mp5_plus":0.8,"ad":52,"ad_plus":3,"as":0.625,"as_plus":0.0213,"ar":24,"ar_plus":5,"mr":30,"mr_plus":1.3,"ms":335,"range":550},"Zoe":{"hp":630,"hp_plus":106,"hp5":6.5,"hp5_plus":0.6,"mp":425,"mp_plus":25,"mp5":8,"mp5_plus":0.65,"ad":58,"ad_plus":3.3,"as":0.625,"as_plus":0.025,"ar":21,"ar_plus":4.7,"mr":30,"mr_plus":1.3,"ms":340,"range":550},"Zyra":{"hp":574,"hp_plus":93,"hp5":5.5,"hp5_plus":0.5,"mp":418,"mp_plus":25,"mp5":13,"mp5_plus":0.4,"ad":53,"ad_plus":3.2,"as":0.625,"as_plus":0.021099999999999997,"ar":29,"ar_plus":4.2,"mr":30,"mr_plus":1.3,"ms":340,"range":575}}