[{"inGameName":"Aatrox","identifier":"aatrox","fileSystemName":"aatrox.json","index":0,"internetLinks":{"wiki":"https://leagueoflegends.fandom.com/wiki/Aatrox/LoL","leagueOfGraphs":"https://www.leagueofgraphs.com//champions/builds/aatrox"}},{"inGameName":"Ahri","identifier":"ahri","fileSystemName":"ahri.json","index":1,"internetLinks":{"wiki":"https://leagueoflegends.fandom.com/wiki/Ahri/LoL","leagueOfGraphs":"https://www.leagueofgraphs.com//champions/builds/ahri"}},{"inGameName":"Akali","identifier":"akali","fileSystemName":"akali.json","index":2,"internetLinks":{"wiki":"https://leagueoflegends.fandom.com/wiki/Akali/LoL","leagueOfGraphs":"https://www.leagueofgraphs.com//champions/builds/akali"}},{"inGameName":"Akshan","identifier":"akshan","fileSystemName":"akshan.json","index":3,"internetLinks":{"wiki":"https://leagueoflegends.fandom.com/wiki/Akshan/LoL","leagueOfGraphs":"https://www.leagueofgraphs.com//champions/builds/akshan"}},{"inGameName":"Alistar","identifier":"alistar","fileSystemName":"alistar.json","index":4,"internetLinks":{"wiki":"https://leagueoflegends.fandom.com/wiki/Alistar/LoL","leagueOfGraphs":"https://www.leagueofgraphs.com//champions/builds/alistar"}},{"inGameName":"Amumu","identifier":"amumu","fileSystemName":"amumu.json","index":5,"internetLinks":{"wiki":"https://leagueoflegends.fandom.com/wiki/Amumu/LoL","leagueOfGraphs":"https://www.leagueofgraphs.com//champions/builds/amumu"}},{"inGameName":"Anivia","identifier":"anivia","fileSystemName":"anivia.json","index":6,"internetLinks":{"wiki":"https://leagueoflegends.fandom.com/wiki/Anivia/LoL","leagueOfGraphs":"https://www.leagueofgraphs.com//champions/builds/anivia"}},{"inGameName":"Annie","identifier":"annie","fileSystemName":"annie.json","index":7,"internetLinks":{"wiki":"https://leagueoflegends.fandom.com/wiki/Annie/LoL","leagueOfGraphs":"https://www.leagueofgraphs.com//champions/builds/annie"}},{"inGameName":"Aphelios","identifier":"aphelios","fileSystemName":"aphelios.json","index":8,"internetLinks":{"wiki":"https://leagueoflegends.fandom.com/wiki/Aphelios/LoL","leagueOfGraphs":"https://www.leagueofgraphs.com//champions/builds/aphelios"}},{"inGameName":"Ashe","identifier":"ashe","fileSystemName":"ashe.json","index":9,"internetLinks":{"wiki":"https://leagueoflegends.fandom.com/wiki/Ashe/LoL","leagueOfGraphs":"https://www.leagueofgraphs.com//champions/builds/ashe"}},{"inGameName":"Aurelion Sol","identifier":"aurelionsol","fileSystemName":"aurelionsol.json","index":10,"internetLinks":{"wiki":"https://leagueoflegends.fandom.com/wiki/Aurelion_Sol/LoL","leagueOfGraphs":"https://www.leagueofgraphs.com//champions/builds/aurelionsol"}},{"inGameName":"Azir","identifier":"azir","fileSystemName":"azir.json","index":11,"internetLinks":{"wiki":"https://leagueoflegends.fandom.com/wiki/Azir/LoL","leagueOfGraphs":"https://www.leagueofgraphs.com//champions/builds/azir"}},{"inGameName":"Bard","identifier":"bard","fileSystemName":"bard.json","index":12,"internetLinks":{"wiki":"https://leagueoflegends.fandom.com/wiki/Bard/LoL","leagueOfGraphs":"https://www.leagueofgraphs.com//champions/builds/bard"}},{"inGameName":"Bel'Veth","identifier":"belveth","fileSystemName":"belveth.json","index":13,"internetLinks":{"wiki":"https://leagueoflegends.fandom.com/wiki/Bel%27Veth/LoL","leagueOfGraphs":"https://www.leagueofgraphs.com//champions/builds/belveth"}},{"inGameName":"Blitzcrank","identifier":"blitzcrank","fileSystemName":"blitzcrank.json","index":14,"internetLinks":{"wiki":"https://leagueoflegends.fandom.com/wiki/Blitzcrank/LoL","leagueOfGraphs":"https://www.leagueofgraphs.com//champions/builds/blitzcrank"}},{"inGameName":"Brand","identifier":"brand","fileSystemName":"brand.json","index":15,"internetLinks":{"wiki":"https://leagueoflegends.fandom.com/wiki/Brand/LoL","leagueOfGraphs":"https://www.leagueofgraphs.com//champions/builds/brand"}},{"inGameName":"Braum","identifier":"braum","fileSystemName":"braum.json","index":16,"internetLinks":{"wiki":"https://leagueoflegends.fandom.com/wiki/Braum/LoL","leagueOfGraphs":"https://www.leagueofgraphs.com//champions/builds/braum"}},{"inGameName":"Caitlyn","identifier":"caitlyn","fileSystemName":"caitlyn.json","index":17,"internetLinks":{"wiki":"https://leagueoflegends.fandom.com/wiki/Caitlyn/LoL","leagueOfGraphs":"https://www.leagueofgraphs.com//champions/builds/caitlyn"}},{"inGameName":"Camille","identifier":"camille","fileSystemName":"camille.json","index":18,"internetLinks":{"wiki":"https://leagueoflegends.fandom.com/wiki/Camille/LoL","leagueOfGraphs":"https://www.leagueofgraphs.com//champions/builds/camille"}},{"inGameName":"Cassiopeia","identifier":"cassiopeia","fileSystemName":"cassiopeia.json","index":19,"internetLinks":{"wiki":"https://leagueoflegends.fandom.com/wiki/Cassiopeia/LoL","leagueOfGraphs":"https://www.leagueofgraphs.com//champions/builds/cassiopeia"}},{"inGameName":"Cho'Gath","identifier":"chogath","fileSystemName":"chogath.json","index":20,"internetLinks":{"wiki":"https://leagueoflegends.fandom.com/wiki/Cho%27Gath/LoL","leagueOfGraphs":"https://www.leagueofgraphs.com//champions/builds/chogath"}},{"inGameName":"Corki","identifier":"corki","fileSystemName":"corki.json","index":21,"internetLinks":{"wiki":"https://leagueoflegends.fandom.com/wiki/Corki/LoL","leagueOfGraphs":"https://www.leagueofgraphs.com//champions/builds/corki"}},{"inGameName":"Darius","identifier":"darius","fileSystemName":"darius.json","index":22,"internetLinks":{"wiki":"https://leagueoflegends.fandom.com/wiki/Darius/LoL","leagueOfGraphs":"https://www.leagueofgraphs.com//champions/builds/darius"}},{"inGameName":"Diana","identifier":"diana","fileSystemName":"diana.json","index":23,"internetLinks":{"wiki":"https://leagueoflegends.fandom.com/wiki/Diana/LoL","leagueOfGraphs":"https://www.leagueofgraphs.com//champions/builds/diana"}},{"inGameName":"Dr. Mundo","identifier":"drmundo","fileSystemName":"drmundo.json","index":24,"internetLinks":{"wiki":"https://leagueoflegends.fandom.com/wiki/Dr._Mundo/LoL","leagueOfGraphs":"https://www.leagueofgraphs.com//champions/builds/drmundo"}},{"inGameName":"Draven","identifier":"draven","fileSystemName":"draven.json","index":25,"internetLinks":{"wiki":"https://leagueoflegends.fandom.com/wiki/Draven/LoL","leagueOfGraphs":"https://www.leagueofgraphs.com//champions/builds/draven"}},{"inGameName":"Ekko","identifier":"ekko","fileSystemName":"ekko.json","index":26,"internetLinks":{"wiki":"https://leagueoflegends.fandom.com/wiki/Ekko/LoL","leagueOfGraphs":"https://www.leagueofgraphs.com//champions/builds/ekko"}},{"inGameName":"Elise","identifier":"elise","fileSystemName":"elise.json","index":27,"internetLinks":{"wiki":"https://leagueoflegends.fandom.com/wiki/Elise/LoL","leagueOfGraphs":"https://www.leagueofgraphs.com//champions/builds/elise"}},{"inGameName":"Evelynn","identifier":"evelynn","fileSystemName":"evelynn.json","index":28,"internetLinks":{"wiki":"https://leagueoflegends.fandom.com/wiki/Evelynn/LoL","leagueOfGraphs":"https://www.leagueofgraphs.com//champions/builds/evelynn"}},{"inGameName":"Ezreal","identifier":"ezreal","fileSystemName":"ezreal.json","index":29,"internetLinks":{"wiki":"https://leagueoflegends.fandom.com/wiki/Ezreal/LoL","leagueOfGraphs":"https://www.leagueofgraphs.com//champions/builds/ezreal"}},{"inGameName":"Fiddlesticks","identifier":"fiddlesticks","fileSystemName":"fiddlesticks.json","index":30,"internetLinks":{"wiki":"https://leagueoflegends.fandom.com/wiki/Fiddlesticks/LoL","leagueOfGraphs":"https://www.leagueofgraphs.com//champions/builds/fiddlesticks"}},{"inGameName":"Fiora","identifier":"fiora","fileSystemName":"fiora.json","index":31,"internetLinks":{"wiki":"https://leagueoflegends.fandom.com/wiki/Fiora/LoL","leagueOfGraphs":"https://www.leagueofgraphs.com//champions/builds/fiora"}},{"inGameName":"Fizz","identifier":"fizz","fileSystemName":"fizz.json","index":32,"internetLinks":{"wiki":"https://leagueoflegends.fandom.com/wiki/Fizz/LoL","leagueOfGraphs":"https://www.leagueofgraphs.com//champions/builds/fizz"}},{"inGameName":"Galio","identifier":"galio","fileSystemName":"galio.json","index":33,"internetLinks":{"wiki":"https://leagueoflegends.fandom.com/wiki/Galio/LoL","leagueOfGraphs":"https://www.leagueofgraphs.com//champions/builds/galio"}},{"inGameName":"Gangplank","identifier":"gangplank","fileSystemName":"gangplank.json","index":34,"internetLinks":{"wiki":"https://leagueoflegends.fandom.com/wiki/Gangplank/LoL","leagueOfGraphs":"https://www.leagueofgraphs.com//champions/builds/gangplank"}},{"inGameName":"Garen","identifier":"garen","fileSystemName":"garen.json","index":35,"internetLinks":{"wiki":"https://leagueoflegends.fandom.com/wiki/Garen/LoL","leagueOfGraphs":"https://www.leagueofgraphs.com//champions/builds/garen"}},{"inGameName":"Gnar","identifier":"gnar","fileSystemName":"gnar.json","index":36,"internetLinks":{"wiki":"https://leagueoflegends.fandom.com/wiki/Gnar/LoL","leagueOfGraphs":"https://www.leagueofgraphs.com//champions/builds/gnar"}},{"inGameName":"Gragas","identifier":"gragas","fileSystemName":"gragas.json","index":37,"internetLinks":{"wiki":"https://leagueoflegends.fandom.com/wiki/Gragas/LoL","leagueOfGraphs":"https://www.leagueofgraphs.com//champions/builds/gragas"}},{"inGameName":"Graves","identifier":"graves","fileSystemName":"graves.json","index":38,"internetLinks":{"wiki":"https://leagueoflegends.fandom.com/wiki/Graves/LoL","leagueOfGraphs":"https://www.leagueofgraphs.com//champions/builds/graves"}},{"inGameName":"Gwen","identifier":"gwen","fileSystemName":"gwen.json","index":39,"internetLinks":{"wiki":"https://leagueoflegends.fandom.com/wiki/Gwen/LoL","leagueOfGraphs":"https://www.leagueofgraphs.com//champions/builds/gwen"}},{"inGameName":"Hecarim","identifier":"hecarim","fileSystemName":"hecarim.json","index":40,"internetLinks":{"wiki":"https://leagueoflegends.fandom.com/wiki/Hecarim/LoL","leagueOfGraphs":"https://www.leagueofgraphs.com//champions/builds/hecarim"}},{"inGameName":"Heimerdinger","identifier":"heimerdinger","fileSystemName":"heimerdinger.json","index":41,"internetLinks":{"wiki":"https://leagueoflegends.fandom.com/wiki/Heimerdinger/LoL","leagueOfGraphs":"https://www.leagueofgraphs.com//champions/builds/heimerdinger"}},{"inGameName":"Illaoi","identifier":"illaoi","fileSystemName":"illaoi.json","index":42,"internetLinks":{"wiki":"https://leagueoflegends.fandom.com/wiki/Illaoi/LoL","leagueOfGraphs":"https://www.leagueofgraphs.com//champions/builds/illaoi"}},{"inGameName":"Irelia","identifier":"irelia","fileSystemName":"irelia.json","index":43,"internetLinks":{"wiki":"https://leagueoflegends.fandom.com/wiki/Irelia/LoL","leagueOfGraphs":"https://www.leagueofgraphs.com//champions/builds/irelia"}},{"inGameName":"Ivern","identifier":"ivern","fileSystemName":"ivern.json","index":44,"internetLinks":{"wiki":"https://leagueoflegends.fandom.com/wiki/Ivern/LoL","leagueOfGraphs":"https://www.leagueofgraphs.com//champions/builds/ivern"}},{"inGameName":"Janna","identifier":"janna","fileSystemName":"janna.json","index":45,"internetLinks":{"wiki":"https://leagueoflegends.fandom.com/wiki/Janna/LoL","leagueOfGraphs":"https://www.leagueofgraphs.com//champions/builds/janna"}},{"inGameName":"Jarvan IV","identifier":"jarvaniv","fileSystemName":"jarvaniv.json","index":46,"internetLinks":{"wiki":"https://leagueoflegends.fandom.com/wiki/Jarvan_IV/LoL","leagueOfGraphs":"https://www.leagueofgraphs.com//champions/builds/jarvaniv"}},{"inGameName":"Jax","identifier":"jax","fileSystemName":"jax.json","index":47,"internetLinks":{"wiki":"https://leagueoflegends.fandom.com/wiki/Jax/LoL","leagueOfGraphs":"https://www.leagueofgraphs.com//champions/builds/jax"}},{"inGameName":"Jayce","identifier":"jayce","fileSystemName":"jayce.json","index":48,"internetLinks":{"wiki":"https://leagueoflegends.fandom.com/wiki/Jayce/LoL","leagueOfGraphs":"https://www.leagueofgraphs.com//champions/builds/jayce"}},{"inGameName":"Jhin","identifier":"jhin","fileSystemName":"jhin.json","index":49,"internetLinks":{"wiki":"https://leagueoflegends.fandom.com/wiki/Jhin/LoL","leagueOfGraphs":"https://www.leagueofgraphs.com//champions/builds/jhin"}},{"inGameName":"Jinx","identifier":"jinx","fileSystemName":"jinx.json","index":50,"internetLinks":{"wiki":"https://leagueoflegends.fandom.com/wiki/Jinx/LoL","leagueOfGraphs":"https://www.leagueofgraphs.com//champions/builds/jinx"}},{"inGameName":"K'Sante","identifier":"ksante","fileSystemName":"ksante.json","index":51,"internetLinks":{"wiki":"https://leagueoflegends.fandom.com/wiki/K%27Sante/LoL","leagueOfGraphs":"https://www.leagueofgraphs.com//champions/builds/ksante"}},{"inGameName":"Kai'Sa","identifier":"kaisa","fileSystemName":"kaisa.json","index":52,"internetLinks":{"wiki":"https://leagueoflegends.fandom.com/wiki/Kai%27Sa/LoL","leagueOfGraphs":"https://www.leagueofgraphs.com//champions/builds/kaisa"}},{"inGameName":"Kalista","identifier":"kalista","fileSystemName":"kalista.json","index":53,"internetLinks":{"wiki":"https://leagueoflegends.fandom.com/wiki/Kalista/LoL","leagueOfGraphs":"https://www.leagueofgraphs.com//champions/builds/kalista"}},{"inGameName":"Karma","identifier":"karma","fileSystemName":"karma.json","index":54,"internetLinks":{"wiki":"https://leagueoflegends.fandom.com/wiki/Karma/LoL","leagueOfGraphs":"https://www.leagueofgraphs.com//champions/builds/karma"}},{"inGameName":"Karthus","identifier":"karthus","fileSystemName":"karthus.json","index":55,"internetLinks":{"wiki":"https://leagueoflegends.fandom.com/wiki/Karthus/LoL","leagueOfGraphs":"https://www.leagueofgraphs.com//champions/builds/karthus"}},{"inGameName":"Kassadin","identifier":"kassadin","fileSystemName":"kassadin.json","index":56,"internetLinks":{"wiki":"https://leagueoflegends.fandom.com/wiki/Kassadin/LoL","leagueOfGraphs":"https://www.leagueofgraphs.com//champions/builds/kassadin"}},{"inGameName":"Katarina","identifier":"katarina","fileSystemName":"katarina.json","index":57,"internetLinks":{"wiki":"https://leagueoflegends.fandom.com/wiki/Katarina/LoL","leagueOfGraphs":"https://www.leagueofgraphs.com//champions/builds/katarina"}},{"inGameName":"Kayle","identifier":"kayle","fileSystemName":"kayle.json","index":58,"internetLinks":{"wiki":"https://leagueoflegends.fandom.com/wiki/Kayle/LoL","leagueOfGraphs":"https://www.leagueofgraphs.com//champions/builds/kayle"}},{"inGameName":"Kayn","identifier":"kayn","fileSystemName":"kayn.json","index":59,"internetLinks":{"wiki":"https://leagueoflegends.fandom.com/wiki/Kayn/LoL","leagueOfGraphs":"https://www.leagueofgraphs.com//champions/builds/kayn"}},{"inGameName":"Kennen","identifier":"kennen","fileSystemName":"kennen.json","index":60,"internetLinks":{"wiki":"https://leagueoflegends.fandom.com/wiki/Kennen/LoL","leagueOfGraphs":"https://www.leagueofgraphs.com//champions/builds/kennen"}},{"inGameName":"Kha'Zix","identifier":"khazix","fileSystemName":"khazix.json","index":61,"internetLinks":{"wiki":"https://leagueoflegends.fandom.com/wiki/Kha%27Zix/LoL","leagueOfGraphs":"https://www.leagueofgraphs.com//champions/builds/khazix"}},{"inGameName":"Kindred","identifier":"kindred","fileSystemName":"kindred.json","index":62,"internetLinks":{"wiki":"https://leagueoflegends.fandom.com/wiki/Kindred/LoL","leagueOfGraphs":"https://www.leagueofgraphs.com//champions/builds/kindred"}},{"inGameName":"Kled","identifier":"kled","fileSystemName":"kled.json","index":63,"internetLinks":{"wiki":"https://leagueoflegends.fandom.com/wiki/Kled/LoL","leagueOfGraphs":"https://www.leagueofgraphs.com//champions/builds/kled"}},{"inGameName":"Kled & Skaarl","identifier":"kledskaarl","fileSystemName":"kledskaarl.json","index":64,"internetLinks":{"wiki":"https://leagueoflegends.fandom.com/wiki/Kled_%26_Skaarl/LoL","leagueOfGraphs":"https://www.leagueofgraphs.com//champions/builds/kled"}},{"inGameName":"Kog'Maw","identifier":"kogmaw","fileSystemName":"kogmaw.json","index":65,"internetLinks":{"wiki":"https://leagueoflegends.fandom.com/wiki/Kog%27Maw/LoL","leagueOfGraphs":"https://www.leagueofgraphs.com//champions/builds/kogmaw"}},{"inGameName":"LeBlanc","identifier":"leblanc","fileSystemName":"leblanc.json","index":66,"internetLinks":{"wiki":"https://leagueoflegends.fandom.com/wiki/LeBlanc/LoL","leagueOfGraphs":"https://www.leagueofgraphs.com//champions/builds/leblanc"}},{"inGameName":"Lee Sin","identifier":"leesin","fileSystemName":"leesin.json","index":67,"internetLinks":{"wiki":"https://leagueoflegends.fandom.com/wiki/Lee_Sin/LoL","leagueOfGraphs":"https://www.leagueofgraphs.com//champions/builds/leesin"}},{"inGameName":"Leona","identifier":"leona","fileSystemName":"leona.json","index":68,"internetLinks":{"wiki":"https://leagueoflegends.fandom.com/wiki/Leona/LoL","leagueOfGraphs":"https://www.leagueofgraphs.com//champions/builds/leona"}},{"inGameName":"Lillia","identifier":"lillia","fileSystemName":"lillia.json","index":69,"internetLinks":{"wiki":"https://leagueoflegends.fandom.com/wiki/Lillia/LoL","leagueOfGraphs":"https://www.leagueofgraphs.com//champions/builds/lillia"}},{"inGameName":"Lissandra","identifier":"lissandra","fileSystemName":"lissandra.json","index":70,"internetLinks":{"wiki":"https://leagueoflegends.fandom.com/wiki/Lissandra/LoL","leagueOfGraphs":"https://www.leagueofgraphs.com//champions/builds/lissandra"}},{"inGameName":"Lucian","identifier":"lucian","fileSystemName":"lucian.json","index":71,"internetLinks":{"wiki":"https://leagueoflegends.fandom.com/wiki/Lucian/LoL","leagueOfGraphs":"https://www.leagueofgraphs.com//champions/builds/lucian"}},{"inGameName":"Lulu","identifier":"lulu","fileSystemName":"lulu.json","index":72,"internetLinks":{"wiki":"https://leagueoflegends.fandom.com/wiki/Lulu/LoL","leagueOfGraphs":"https://www.leagueofgraphs.com//champions/builds/lulu"}},{"inGameName":"Lux","identifier":"lux","fileSystemName":"lux.json","index":73,"internetLinks":{"wiki":"https://leagueoflegends.fandom.com/wiki/Lux/LoL","leagueOfGraphs":"https://www.leagueofgraphs.com//champions/builds/lux"}},{"inGameName":"Malphite","identifier":"malphite","fileSystemName":"malphite.json","index":74,"internetLinks":{"wiki":"https://leagueoflegends.fandom.com/wiki/Malphite/LoL","leagueOfGraphs":"https://www.leagueofgraphs.com//champions/builds/malphite"}},{"inGameName":"Malzahar","identifier":"malzahar","fileSystemName":"malzahar.json","index":75,"internetLinks":{"wiki":"https://leagueoflegends.fandom.com/wiki/Malzahar/LoL","leagueOfGraphs":"https://www.leagueofgraphs.com//champions/builds/malzahar"}},{"inGameName":"Maokai","identifier":"maokai","fileSystemName":"maokai.json","index":76,"internetLinks":{"wiki":"https://leagueoflegends.fandom.com/wiki/Maokai/LoL","leagueOfGraphs":"https://www.leagueofgraphs.com//champions/builds/maokai"}},{"inGameName":"Master Yi","identifier":"masteryi","fileSystemName":"masteryi.json","index":77,"internetLinks":{"wiki":"https://leagueoflegends.fandom.com/wiki/Master_Yi/LoL","leagueOfGraphs":"https://www.leagueofgraphs.com//champions/builds/masteryi"}},{"inGameName":"Mega Gnar","identifier":"megagnar","fileSystemName":"megagnar.json","index":78,"internetLinks":{"wiki":"https://leagueoflegends.fandom.com/wiki/Mega_Gnar/LoL","leagueOfGraphs":"https://www.leagueofgraphs.com//champions/builds/gnar"}},{"inGameName":"Miss Fortune","identifier":"missfortune","fileSystemName":"missfortune.json","index":79,"internetLinks":{"wiki":"https://leagueoflegends.fandom.com/wiki/Miss_Fortune/LoL","leagueOfGraphs":"https://www.leagueofgraphs.com//champions/builds/missfortune"}},{"inGameName":"Mordekaiser","identifier":"mordekaiser","fileSystemName":"mordekaiser.json","index":80,"internetLinks":{"wiki":"https://leagueoflegends.fandom.com/wiki/Mordekaiser/LoL","leagueOfGraphs":"https://www.leagueofgraphs.com//champions/builds/mordekaiser"}},{"inGameName":"Morgana","identifier":"morgana","fileSystemName":"morgana.json","index":81,"internetLinks":{"wiki":"https://leagueoflegends.fandom.com/wiki/Morgana/LoL","leagueOfGraphs":"https://www.leagueofgraphs.com//champions/builds/morgana"}},{"inGameName":"Nami","identifier":"nami","fileSystemName":"nami.json","index":82,"internetLinks":{"wiki":"https://leagueoflegends.fandom.com/wiki/Nami/LoL","leagueOfGraphs":"https://www.leagueofgraphs.com//champions/builds/nami"}},{"inGameName":"Nasus","identifier":"nasus","fileSystemName":"nasus.json","index":83,"internetLinks":{"wiki":"https://leagueoflegends.fandom.com/wiki/Nasus/LoL","leagueOfGraphs":"https://www.leagueofgraphs.com//champions/builds/nasus"}},{"inGameName":"Nautilus","identifier":"nautilus","fileSystemName":"nautilus.json","index":84,"internetLinks":{"wiki":"https://leagueoflegends.fandom.com/wiki/Nautilus/LoL","leagueOfGraphs":"https://www.leagueofgraphs.com//champions/builds/nautilus"}},{"inGameName":"Neeko","identifier":"neeko","fileSystemName":"neeko.json","index":85,"internetLinks":{"wiki":"https://leagueoflegends.fandom.com/wiki/Neeko/LoL","leagueOfGraphs":"https://www.leagueofgraphs.com//champions/builds/neeko"}},{"inGameName":"Nidalee","identifier":"nidalee","fileSystemName":"nidalee.json","index":86,"internetLinks":{"wiki":"https://leagueoflegends.fandom.com/wiki/Nidalee/LoL","leagueOfGraphs":"https://www.leagueofgraphs.com//champions/builds/nidalee"}},{"inGameName":"Nilah","identifier":"nilah","fileSystemName":"nilah.json","index":87,"internetLinks":{"wiki":"https://leagueoflegends.fandom.com/wiki/Nilah/LoL","leagueOfGraphs":"https://www.leagueofgraphs.com//champions/builds/nilah"}},{"inGameName":"Nocturne","identifier":"nocturne","fileSystemName":"nocturne.json","index":88,"internetLinks":{"wiki":"https://leagueoflegends.fandom.com/wiki/Nocturne/LoL","leagueOfGraphs":"https://www.leagueofgraphs.com//champions/builds/nocturne"}},{"inGameName":"Nunu & Willump","identifier":"nunuwillump","fileSystemName":"nunuwillump.json","index":89,"internetLinks":{"wiki":"https://leagueoflegends.fandom.com/wiki/Nunu_%26_Willump/LoL","leagueOfGraphs":"https://www.leagueofgraphs.com//champions/builds/nunu"}},{"inGameName":"Olaf","identifier":"olaf","fileSystemName":"olaf.json","index":90,"internetLinks":{"wiki":"https://leagueoflegends.fandom.com/wiki/Olaf/LoL","leagueOfGraphs":"https://www.leagueofgraphs.com//champions/builds/olaf"}},{"inGameName":"Orianna","identifier":"orianna","fileSystemName":"orianna.json","index":91,"internetLinks":{"wiki":"https://leagueoflegends.fandom.com/wiki/Orianna/LoL","leagueOfGraphs":"https://www.leagueofgraphs.com//champions/builds/orianna"}},{"inGameName":"Ornn","identifier":"ornn","fileSystemName":"ornn.json","index":92,"internetLinks":{"wiki":"https://leagueoflegends.fandom.com/wiki/Ornn/LoL","leagueOfGraphs":"https://www.leagueofgraphs.com//champions/builds/ornn"}},{"inGameName":"Pantheon","identifier":"pantheon","fileSystemName":"pantheon.json","index":93,"internetLinks":{"wiki":"https://leagueoflegends.fandom.com/wiki/Pantheon/LoL","leagueOfGraphs":"https://www.leagueofgraphs.com//champions/builds/pantheon"}},{"inGameName":"Poppy","identifier":"poppy","fileSystemName":"poppy.json","index":94,"internetLinks":{"wiki":"https://leagueoflegends.fandom.com/wiki/Poppy/LoL","leagueOfGraphs":"https://www.leagueofgraphs.com//champions/builds/poppy"}},{"inGameName":"Pyke","identifier":"pyke","fileSystemName":"pyke.json","index":95,"internetLinks":{"wiki":"https://leagueoflegends.fandom.com/wiki/Pyke/LoL","leagueOfGraphs":"https://www.leagueofgraphs.com//champions/builds/pyke"}},{"inGameName":"Qiyana","identifier":"qiyana","fileSystemName":"qiyana.json","index":96,"internetLinks":{"wiki":"https://leagueoflegends.fandom.com/wiki/Qiyana/LoL","leagueOfGraphs":"https://www.leagueofgraphs.com//champions/builds/qiyana"}},{"inGameName":"Quinn","identifier":"quinn","fileSystemName":"quinn.json","index":97,"internetLinks":{"wiki":"https://leagueoflegends.fandom.com/wiki/Quinn/LoL","leagueOfGraphs":"https://www.leagueofgraphs.com//champions/builds/quinn"}},{"inGameName":"Rakan","identifier":"rakan","fileSystemName":"rakan.json","index":98,"internetLinks":{"wiki":"https://leagueoflegends.fandom.com/wiki/Rakan/LoL","leagueOfGraphs":"https://www.leagueofgraphs.com//champions/builds/rakan"}},{"inGameName":"Rammus","identifier":"rammus","fileSystemName":"rammus.json","index":99,"internetLinks":{"wiki":"https://leagueoflegends.fandom.com/wiki/Rammus/LoL","leagueOfGraphs":"https://www.leagueofgraphs.com//champions/builds/rammus"}},{"inGameName":"Rek'Sai","identifier":"reksai","fileSystemName":"reksai.json","index":100,"internetLinks":{"wiki":"https://leagueoflegends.fandom.com/wiki/Rek%27Sai/LoL","leagueOfGraphs":"https://www.leagueofgraphs.com//champions/builds/reksai"}},{"inGameName":"Rell","identifier":"rell","fileSystemName":"rell.json","index":101,"internetLinks":{"wiki":"https://leagueoflegends.fandom.com/wiki/Rell/LoL","leagueOfGraphs":"https://www.leagueofgraphs.com//champions/builds/rell"}},{"inGameName":"Renata Glasc","identifier":"renataglasc","fileSystemName":"renataglasc.json","index":102,"internetLinks":{"wiki":"https://leagueoflegends.fandom.com/wiki/Renata_Glasc/LoL","leagueOfGraphs":"https://www.leagueofgraphs.com//champions/builds/renata"}},{"inGameName":"Renekton","identifier":"renekton","fileSystemName":"renekton.json","index":103,"internetLinks":{"wiki":"https://leagueoflegends.fandom.com/wiki/Renekton/LoL","leagueOfGraphs":"https://www.leagueofgraphs.com//champions/builds/renekton"}},{"inGameName":"Rengar","identifier":"rengar","fileSystemName":"rengar.json","index":104,"internetLinks":{"wiki":"https://leagueoflegends.fandom.com/wiki/Rengar/LoL","leagueOfGraphs":"https://www.leagueofgraphs.com//champions/builds/rengar"}},{"inGameName":"Riven","identifier":"riven","fileSystemName":"riven.json","index":105,"internetLinks":{"wiki":"https://leagueoflegends.fandom.com/wiki/Riven/LoL","leagueOfGraphs":"https://www.leagueofgraphs.com//champions/builds/riven"}},{"inGameName":"Rumble","identifier":"rumble","fileSystemName":"rumble.json","index":106,"internetLinks":{"wiki":"https://leagueoflegends.fandom.com/wiki/Rumble/LoL","leagueOfGraphs":"https://www.leagueofgraphs.com//champions/builds/rumble"}},{"inGameName":"Ryze","identifier":"ryze","fileSystemName":"ryze.json","index":107,"internetLinks":{"wiki":"https://leagueoflegends.fandom.com/wiki/Ryze/LoL","leagueOfGraphs":"https://www.leagueofgraphs.com//champions/builds/ryze"}},{"inGameName":"Samira","identifier":"samira","fileSystemName":"samira.json","index":108,"internetLinks":{"wiki":"https://leagueoflegends.fandom.com/wiki/Samira/LoL","leagueOfGraphs":"https://www.leagueofgraphs.com//champions/builds/samira"}},{"inGameName":"Sejuani","identifier":"sejuani","fileSystemName":"sejuani.json","index":109,"internetLinks":{"wiki":"https://leagueoflegends.fandom.com/wiki/Sejuani/LoL","leagueOfGraphs":"https://www.leagueofgraphs.com//champions/builds/sejuani"}},{"inGameName":"Senna","identifier":"senna","fileSystemName":"senna.json","index":110,"internetLinks":{"wiki":"https://leagueoflegends.fandom.com/wiki/Senna/LoL","leagueOfGraphs":"https://www.leagueofgraphs.com//champions/builds/senna"}},{"inGameName":"Seraphine","identifier":"seraphine","fileSystemName":"seraphine.json","index":111,"internetLinks":{"wiki":"https://leagueoflegends.fandom.com/wiki/Seraphine/LoL","leagueOfGraphs":"https://www.leagueofgraphs.com//champions/builds/seraphine"}},{"inGameName":"Sett","identifier":"sett","fileSystemName":"sett.json","index":112,"internetLinks":{"wiki":"https://leagueoflegends.fandom.com/wiki/Sett/LoL","leagueOfGraphs":"https://www.leagueofgraphs.com//champions/builds/sett"}},{"inGameName":"Shaco","identifier":"shaco","fileSystemName":"shaco.json","index":113,"internetLinks":{"wiki":"https://leagueoflegends.fandom.com/wiki/Shaco/LoL","leagueOfGraphs":"https://www.leagueofgraphs.com//champions/builds/shaco"}},{"inGameName":"Shen","identifier":"shen","fileSystemName":"shen.json","index":114,"internetLinks":{"wiki":"https://leagueoflegends.fandom.com/wiki/Shen/LoL","leagueOfGraphs":"https://www.leagueofgraphs.com//champions/builds/shen"}},{"inGameName":"Shyvana","identifier":"shyvana","fileSystemName":"shyvana.json","index":115,"internetLinks":{"wiki":"https://leagueoflegends.fandom.com/wiki/Shyvana/LoL","leagueOfGraphs":"https://www.leagueofgraphs.com//champions/builds/shyvana"}},{"inGameName":"Singed","identifier":"singed","fileSystemName":"singed.json","index":116,"internetLinks":{"wiki":"https://leagueoflegends.fandom.com/wiki/Singed/LoL","leagueOfGraphs":"https://www.leagueofgraphs.com//champions/builds/singed"}},{"inGameName":"Sion","identifier":"sion","fileSystemName":"sion.json","index":117,"internetLinks":{"wiki":"https://leagueoflegends.fandom.com/wiki/Sion/LoL","leagueOfGraphs":"https://www.leagueofgraphs.com//champions/builds/sion"}},{"inGameName":"Sivir","identifier":"sivir","fileSystemName":"sivir.json","index":118,"internetLinks":{"wiki":"https://leagueoflegends.fandom.com/wiki/Sivir/LoL","leagueOfGraphs":"https://www.leagueofgraphs.com//champions/builds/sivir"}},{"inGameName":"Skarner","identifier":"skarner","fileSystemName":"skarner.json","index":119,"internetLinks":{"wiki":"https://leagueoflegends.fandom.com/wiki/Skarner/LoL","leagueOfGraphs":"https://www.leagueofgraphs.com//champions/builds/skarner"}},{"inGameName":"Sona","identifier":"sona","fileSystemName":"sona.json","index":120,"internetLinks":{"wiki":"https://leagueoflegends.fandom.com/wiki/Sona/LoL","leagueOfGraphs":"https://www.leagueofgraphs.com//champions/builds/sona"}},{"inGameName":"Soraka","identifier":"soraka","fileSystemName":"soraka.json","index":121,"internetLinks":{"wiki":"https://leagueoflegends.fandom.com/wiki/Soraka/LoL","leagueOfGraphs":"https://www.leagueofgraphs.com//champions/builds/soraka"}},{"inGameName":"Swain","identifier":"swain","fileSystemName":"swain.json","index":122,"internetLinks":{"wiki":"https://leagueoflegends.fandom.com/wiki/Swain/LoL","leagueOfGraphs":"https://www.leagueofgraphs.com//champions/builds/swain"}},{"inGameName":"Sylas","identifier":"sylas","fileSystemName":"sylas.json","index":123,"internetLinks":{"wiki":"https://leagueoflegends.fandom.com/wiki/Sylas/LoL","leagueOfGraphs":"https://www.leagueofgraphs.com//champions/builds/sylas"}},{"inGameName":"Syndra","identifier":"syndra","fileSystemName":"syndra.json","index":124,"internetLinks":{"wiki":"https://leagueoflegends.fandom.com/wiki/Syndra/LoL","leagueOfGraphs":"https://www.leagueofgraphs.com//champions/builds/syndra"}},{"inGameName":"Tahm Kench","identifier":"tahmkench","fileSystemName":"tahmkench.json","index":125,"internetLinks":{"wiki":"https://leagueoflegends.fandom.com/wiki/Tahm_Kench/LoL","leagueOfGraphs":"https://www.leagueofgraphs.com//champions/builds/tahmkench"}},{"inGameName":"Taliyah","identifier":"taliyah","fileSystemName":"taliyah.json","index":126,"internetLinks":{"wiki":"https://leagueoflegends.fandom.com/wiki/Taliyah/LoL","leagueOfGraphs":"https://www.leagueofgraphs.com//champions/builds/taliyah"}},{"inGameName":"Talon","identifier":"talon","fileSystemName":"talon.json","index":127,"internetLinks":{"wiki":"https://leagueoflegends.fandom.com/wiki/Talon/LoL","leagueOfGraphs":"https://www.leagueofgraphs.com//champions/builds/talon"}},{"inGameName":"Taric","identifier":"taric","fileSystemName":"taric.json","index":128,"internetLinks":{"wiki":"https://leagueoflegends.fandom.com/wiki/Taric/LoL","leagueOfGraphs":"https://www.leagueofgraphs.com//champions/builds/taric"}},{"inGameName":"Teemo","identifier":"teemo","fileSystemName":"teemo.json","index":129,"internetLinks":{"wiki":"https://leagueoflegends.fandom.com/wiki/Teemo/LoL","leagueOfGraphs":"https://www.leagueofgraphs.com//champions/builds/teemo"}},{"inGameName":"Thresh","identifier":"thresh","fileSystemName":"thresh.json","index":130,"internetLinks":{"wiki":"https://leagueoflegends.fandom.com/wiki/Thresh/LoL","leagueOfGraphs":"https://www.leagueofgraphs.com//champions/builds/thresh"}},{"inGameName":"Tristana","identifier":"tristana","fileSystemName":"tristana.json","index":131,"internetLinks":{"wiki":"https://leagueoflegends.fandom.com/wiki/Tristana/LoL","leagueOfGraphs":"https://www.leagueofgraphs.com//champions/builds/tristana"}},{"inGameName":"Trundle","identifier":"trundle","fileSystemName":"trundle.json","index":132,"internetLinks":{"wiki":"https://leagueoflegends.fandom.com/wiki/Trundle/LoL","leagueOfGraphs":"https://www.leagueofgraphs.com//champions/builds/trundle"}},{"inGameName":"Tryndamere","identifier":"tryndamere","fileSystemName":"tryndamere.json","index":133,"internetLinks":{"wiki":"https://leagueoflegends.fandom.com/wiki/Tryndamere/LoL","leagueOfGraphs":"https://www.leagueofgraphs.com//champions/builds/tryndamere"}},{"inGameName":"Twisted Fate","identifier":"twistedfate","fileSystemName":"twistedfate.json","index":134,"internetLinks":{"wiki":"https://leagueoflegends.fandom.com/wiki/Twisted_Fate/LoL","leagueOfGraphs":"https://www.leagueofgraphs.com//champions/builds/twistedfate"}},{"inGameName":"Twitch","identifier":"twitch","fileSystemName":"twitch.json","index":135,"internetLinks":{"wiki":"https://leagueoflegends.fandom.com/wiki/Twitch/LoL","leagueOfGraphs":"https://www.leagueofgraphs.com//champions/builds/twitch"}},{"inGameName":"Udyr","identifier":"udyr","fileSystemName":"udyr.json","index":136,"internetLinks":{"wiki":"https://leagueoflegends.fandom.com/wiki/Udyr/LoL","leagueOfGraphs":"https://www.leagueofgraphs.com//champions/builds/udyr"}},{"inGameName":"Urgot","identifier":"urgot","fileSystemName":"urgot.json","index":137,"internetLinks":{"wiki":"https://leagueoflegends.fandom.com/wiki/Urgot/LoL","leagueOfGraphs":"https://www.leagueofgraphs.com//champions/builds/urgot"}},{"inGameName":"Varus","identifier":"varus","fileSystemName":"varus.json","index":138,"internetLinks":{"wiki":"https://leagueoflegends.fandom.com/wiki/Varus/LoL","leagueOfGraphs":"https://www.leagueofgraphs.com//champions/builds/varus"}},{"inGameName":"Vayne","identifier":"vayne","fileSystemName":"vayne.json","index":139,"internetLinks":{"wiki":"https://leagueoflegends.fandom.com/wiki/Vayne/LoL","leagueOfGraphs":"https://www.leagueofgraphs.com//champions/builds/vayne"}},{"inGameName":"Veigar","identifier":"veigar","fileSystemName":"veigar.json","index":140,"internetLinks":{"wiki":"https://leagueoflegends.fandom.com/wiki/Veigar/LoL","leagueOfGraphs":"https://www.leagueofgraphs.com//champions/builds/veigar"}},{"inGameName":"Vel'Koz","identifier":"velkoz","fileSystemName":"velkoz.json","index":141,"internetLinks":{"wiki":"https://leagueoflegends.fandom.com/wiki/Vel%27Koz/LoL","leagueOfGraphs":"https://www.leagueofgraphs.com//champions/builds/velkoz"}},{"inGameName":"Vex","identifier":"vex","fileSystemName":"vex.json","index":142,"internetLinks":{"wiki":"https://leagueoflegends.fandom.com/wiki/Vex/LoL","leagueOfGraphs":"https://www.leagueofgraphs.com//champions/builds/vex"}},{"inGameName":"Vi","identifier":"vi","fileSystemName":"vi.json","index":143,"internetLinks":{"wiki":"https://leagueoflegends.fandom.com/wiki/Vi/LoL","leagueOfGraphs":"https://www.leagueofgraphs.com//champions/builds/vi"}},{"inGameName":"Viego","identifier":"viego","fileSystemName":"viego.json","index":144,"internetLinks":{"wiki":"https://leagueoflegends.fandom.com/wiki/Viego/LoL","leagueOfGraphs":"https://www.leagueofgraphs.com//champions/builds/viego"}},{"inGameName":"Viktor","identifier":"viktor","fileSystemName":"viktor.json","index":145,"internetLinks":{"wiki":"https://leagueoflegends.fandom.com/wiki/Viktor/LoL","leagueOfGraphs":"https://www.leagueofgraphs.com//champions/builds/viktor"}},{"inGameName":"Vladimir","identifier":"vladimir","fileSystemName":"vladimir.json","index":146,"internetLinks":{"wiki":"https://leagueoflegends.fandom.com/wiki/Vladimir/LoL","leagueOfGraphs":"https://www.leagueofgraphs.com//champions/builds/vladimir"}},{"inGameName":"Volibear","identifier":"volibear","fileSystemName":"volibear.json","index":147,"internetLinks":{"wiki":"https://leagueoflegends.fandom.com/wiki/Volibear/LoL","leagueOfGraphs":"https://www.leagueofgraphs.com//champions/builds/volibear"}},{"inGameName":"Warwick","identifier":"warwick","fileSystemName":"warwick.json","index":148,"internetLinks":{"wiki":"https://leagueoflegends.fandom.com/wiki/Warwick/LoL","leagueOfGraphs":"https://www.leagueofgraphs.com//champions/builds/warwick"}},{"inGameName":"Wukong","identifier":"wukong","fileSystemName":"wukong.json","index":149,"internetLinks":{"wiki":"https://leagueoflegends.fandom.com/wiki/Wukong/LoL","leagueOfGraphs":"https://www.leagueofgraphs.com//champions/builds/monkeyking"}},{"inGameName":"Xayah","identifier":"xayah","fileSystemName":"xayah.json","index":150,"internetLinks":{"wiki":"https://leagueoflegends.fandom.com/wiki/Xayah/LoL","leagueOfGraphs":"https://www.leagueofgraphs.com//champions/builds/xayah"}},{"inGameName":"Xerath","identifier":"xerath","fileSystemName":"xerath.json","index":151,"internetLinks":{"wiki":"https://leagueoflegends.fandom.com/wiki/Xerath/LoL","leagueOfGraphs":"https://www.leagueofgraphs.com//champions/builds/xerath"}},{"inGameName":"Xin Zhao","identifier":"xinzhao","fileSystemName":"xinzhao.json","index":152,"internetLinks":{"wiki":"https://leagueoflegends.fandom.com/wiki/Xin_Zhao/LoL","leagueOfGraphs":"https://www.leagueofgraphs.com//champions/builds/xinzhao"}},{"inGameName":"Yasuo","identifier":"yasuo","fileSystemName":"yasuo.json","index":153,"internetLinks":{"wiki":"https://leagueoflegends.fandom.com/wiki/Yasuo/LoL","leagueOfGraphs":"https://www.leagueofgraphs.com//champions/builds/yasuo"}},{"inGameName":"Yone","identifier":"yone","fileSystemName":"yone.json","index":154,"internetLinks":{"wiki":"https://leagueoflegends.fandom.com/wiki/Yone/LoL","leagueOfGraphs":"https://www.leagueofgraphs.com//champions/builds/yone"}},{"inGameName":"Yorick","identifier":"yorick","fileSystemName":"yorick.json","index":155,"internetLinks":{"wiki":"https://leagueoflegends.fandom.com/wiki/Yorick/LoL","leagueOfGraphs":"https://www.leagueofgraphs.com//champions/builds/yorick"}},{"inGameName":"Yuumi","identifier":"yuumi","fileSystemName":"yuumi.json","index":156,"internetLinks":{"wiki":"https://leagueoflegends.fandom.com/wiki/Yuumi/LoL","leagueOfGraphs":"https://www.leagueofgraphs.com//champions/builds/yuumi"}},{"inGameName":"Zac","identifier":"zac","fileSystemName":"zac.json","index":157,"internetLinks":{"wiki":"https://leagueoflegends.fandom.com/wiki/Zac/LoL","leagueOfGraphs":"https://www.leagueofgraphs.com//champions/builds/zac"}},{"inGameName":"Zed","identifier":"zed","fileSystemName":"zed.json","index":158,"internetLinks":{"wiki":"https://leagueoflegends.fandom.com/wiki/Zed/LoL","leagueOfGraphs":"https://www.leagueofgraphs.com//champions/builds/zed"}},{"inGameName":"Zeri","identifier":"zeri","fileSystemName":"zeri.json","index":159,"internetLinks":{"wiki":"https://leagueoflegends.fandom.com/wiki/Zeri/LoL","leagueOfGraphs":"https://www.leagueofgraphs.com//champions/builds/zeri"}},{"inGameName":"Ziggs","identifier":"ziggs","fileSystemName":"ziggs.json","index":160,"internetLinks":{"wiki":"https://leagueoflegends.fandom.com/wiki/Ziggs/LoL","leagueOfGraphs":"https://www.leagueofgraphs.com//champions/builds/ziggs"}},{"inGameName":"Zilean","identifier":"zilean","fileSystemName":"zilean.json","index":161,"internetLinks":{"wiki":"https://leagueoflegends.fandom.com/wiki/Zilean/LoL","leagueOfGraphs":"https://www.leagueofgraphs.com//champions/builds/zilean"}},{"inGameName":"Zoe","identifier":"zoe","fileSystemName":"zoe.json","index":162,"internetLinks":{"wiki":"https://leagueoflegends.fandom.com/wiki/Zoe/LoL","leagueOfGraphs":"https://www.leagueofgraphs.com//champions/builds/zoe"}},{"inGameName":"Zyra","identifier":"zyra","fileSystemName":"zyra.json","index":163,"internetLinks":{"wiki":"https://leagueoflegends.fandom.com/wiki/Zyra/LoL","leagueOfGraphs":"https://www.leagueofgraphs.com//champions/builds/zyra"}}]